[
  {
    "problem_id": "18(UnknownSource)-지수함수와로그함수의교점,삼각형의넓이",
    "content": "# 18. (Unknown Source) - 지수함수와 로그함수의 교점, 삼각형의 넓이\n\n## Problem\n\n곡선 $y=a^{x-4}$ $(a>1)$이 직선 $y=4$와 만나는 점을 A,\n\n곡선 $y=\\log_a x$가 직선 $x=4$와 만나는 점을 B,\n\n점 A에서 직선 $y=x$에 대한 수선의 발을 C라 하자.\n\n삼각형 ABC의 넓이가 6일 때, $a$의 값은? [4점]\n\n## Choices\n\n① $2^{\\frac{1}{6}}$\n② $2^{\\frac{1}{3}}$\n③ $2^{\\frac{1}{2}}$\n④ $2^2$\n⑤ $2^{\\frac{5}{2}}$\n\n**Answer**: ②\n**Difficulty**: 4점\n**Score**: 4\n**Type**: multiple choice\n\n---\n\n## Solution\n\n[FIGURE: 좌표평면에 곡선 $y=a^{x-4}$, $y=\\log_a x$, 직선 $y=x$, $y=4$, $x=4$가 그려져 있고, 점 A, B, C가 표시되어 있음]\n\n문제의 조건에 의해\n\n$\\begin{cases} y=a^{x-4}$와 $y=4$의 교점이 A $\\Rightarrow$ A$(4+2\\log_a 2, 4)$ \\\\ y=\\log_a x$와 $x=4$의 교점이 B $\\Rightarrow$ B$(4, 2\\log_a 2)$ \\end{cases}$\n\n이므로\n\n$\\overline{AC}\\perp$(직선 $y=x$) $\\Rightarrow$ (직선 AC의 기울기)$=-1$\n\n$\\Rightarrow$ 직선 AC의 방정식: $x+y=8+2\\log_a 2$\n\n$\\Rightarrow$ (B에서 직선 AC 까지의 거리)$=\\frac{4}{\\sqrt{2}}$\n\n임을 알 수 있다. 또한,\n\n$\\overline{AC}=\\frac{2\\log_a 2}{\\sqrt{2}}$ ($\\because$ 점 A에서 $y=x$까지의 거리)\n\n이므로\n\n(삼각형 ABC의 넓이)$=\\frac{1}{2}\\times\\frac{2\\log_a 2}{\\sqrt{2}}\\times\\frac{4}{\\sqrt{2}}=2\\log_a 2$\n\n이고, 문제의 조건에서 이 값이 6이므로\n\n$$\\log_a 2=3 \\Rightarrow a=2^{\\frac{1}{3}}$$\n\n을 얻는다.\n\n[다른 풀이]\n\n점 A를 직선 $y=x$에 대하여 대칭이동한 점을 D라 하면\n\n(삼각형 ABC의 넓이)$=6 \\Rightarrow$ (삼각형 ABD의 넓이)$=12$\n\n이므로 점 $(4, 4)$를 H라 하면\n\n$$\\frac{1}{2}\\times\\overline{BD}\\times\\overline{AH}=12$$\n\n임을 이용하여 전개할 수 있다.\n\n[FIGURE: 위와 유사하나 점 D와 H가 추가로 표시되어 있음]\n\n---",
    "content_source": "FileLoop",
    "content_length": 1338,
    "skel_status": "ok",
    "dna_status": "dna_missing",
    "needed_neurons": [],
    "needed_dna": [
      {
        "id": "G27",
        "name": "수선의 발",
        "signature": "(점, 직선) → 점",
        "reason": "점에서 직선에 내린 수선의 발을 나타내는 기하 구조. 기존 DNA에 없음."
      }
    ],
    "previous_analysis": "",
    "previous_matching": "1. a^{x-4}=4 → 연산2(로그-지수 변환)로 x-4=log_a 4\n2. log_a 4=2log_a 2 → 연산17(로그 거듭제곱법칙)\n3. y=log_a 4=2log_a 2 → 연산17\n4. a>1에서 log_a 2>0 확인 → 사실12, 사실62, 사실51\n5. A의 y=x 대칭점 구하기 → 연산20\n6. C=A와 대칭점의 중점 → 연산12\n7. AC 길이 → 연산11\n8. 직선 AC 방정식 → 사실15, 연산30\n9. B에서 직선 AC까지 거리 → 연산19\n10. 삼각형 넓이 → 연산13\n11. 2log_a 2=6 풀기 → 연산2\n12. y=a^x와 y=log_a x의 대칭 → 사실3",
    "previous_matched": [
      "연산2",
      "연산17",
      "전략25",
      "사실62",
      "사실51",
      "연산20",
      "연산12",
      "연산11",
      "사실15",
      "연산30",
      "연산19",
      "연산13",
      "전략2",
      "사실12"
    ],
    "previous_skeleton": [
      {
        "from": "단서A",
        "to": "note1",
        "neuron": "연산2",
        "note": "$a^{x-4}=4$에서 $x-4=\\log_a 4$이다",
        "step": 1
      },
      {
        "from": "note1",
        "to": "note2",
        "neuron": "연산17",
        "note": "$x = 4+\\log_a 4 = 4+2\\log_a 2$이다",
        "step": 1
      },
      {
        "from": "note2",
        "to": "note3",
        "neuron": "전략25",
        "note": "$A = (4+2\\log_a 2,\\; 4)$이다",
        "step": 1
      },
      {
        "from": "단서B",
        "to": "note4",
        "neuron": "전략25",
        "note": "$x=4$를 대입하면 $y=\\log_a 4$이다",
        "step": 2
      },
      {
        "from": "note4",
        "to": "note5",
        "neuron": "연산17",
        "note": "$\\log_a 4 = 2\\log_a 2$이므로 $B = (4,\\; 2\\log_a 2)$이다",
        "step": 2
      },
      {
        "from": "단서D",
        "to": "note6",
        "neuron": "사실12",
        "note": "$a>1$이므로 $y=\\log_a x$는 순증가이다",
        "main": false,
        "step": 3
      },
      {
        "from": "note6",
        "to": "note7",
        "neuron": "사실51",
        "note": "$2>1$이고 $\\log_a 1=0$이므로 $\\log_a 2 > 0$이다",
        "main": false,
        "step": 3
      },
      {
        "from": [
          "note3",
          "note5",
          "note7"
        ],
        "to": "note8",
        "neuron": "전략25",
        "note": "$t = 2\\log_a 2 > 0$으로 놓으면 $A=(4+t,4)$, $B=(4,t)$이다",
        "step": 3
      },
      {
        "from": "note8",
        "to": "note9",
        "neuron": "연산20",
        "note": "점 $A=(4+t,4)$를 직선 $y=x$에 대해 대칭이동하면 $(4, 4+t)$이다",
        "main": false,
        "step": 4
      },
      {
        "from": [
          "note8",
          "note9"
        ],
        "to": "note10",
        "neuron": "연산12",
        "note": "$C$는 $A=(4+t,4)$와 대칭점 $(4,4+t)$의 중점이므로 $C=\\left(\\frac{8+t}{2},\\frac{8+t}{2}\\right)$이다",
        "step": 4
      },
      {
        "from": [
          "note8",
          "note10"
        ],
        "to": "note11",
        "neuron": "연산11",
        "note": "$AC = \\sqrt{\\left(\\frac{t}{2}\\right)^2+\\left(\\frac{t}{2}\\right)^2} = \\frac{t}{\\sqrt{2}}$이다",
        "step": 5
      },
      {
        "from": "note8",
        "to": "note12",
        "neuron": "사실15",
        "note": "직선 AC는 직선 $y=x$(기울기 1)에 수직이므로 기울기가 $-1$이다",
        "main": false,
        "step": 6
      },
      {
        "from": [
          "note12",
          "note8"
        ],
        "to": "note13",
        "neuron": "연산30",
        "note": "직선 AC의 방정식은 $x+y = 8+t$이다",
        "step": 6
      },
      {
        "from": [
          "note5",
          "note13"
        ],
        "to": "note14",
        "neuron": "연산19",
        "note": "점 $B=(4,t)$에서 직선 $x+y-(8+t)=0$까지의 거리는 $\\frac{|4+t-8-t|}{\\sqrt{2}}=\\frac{4}{\\sqrt{2}}$이다",
        "step": 6
      },
      {
        "from": [
          "note11",
          "note14"
        ],
        "to": "note15",
        "neuron": "연산13",
        "note": "삼각형 ABC의 넓이는 $\\frac{1}{2}\\times\\frac{t}{\\sqrt{2}}\\times\\frac{4}{\\sqrt{2}} = t = 2\\log_a 2$이다",
        "step": 7
      },
      {
        "from": [
          "note15",
          "단서E"
        ],
        "to": "note16",
        "neuron": "전략2",
        "note": "$2\\log_a 2 = 6$에서 $\\log_a 2 = 3$이다",
        "step": 8
      },
      {
        "from": "note16",
        "to": "END",
        "neuron": "연산2",
        "note": "$a^3 = 2$에서 $a = 2^{1/3}$이다",
        "step": 8
      }
    ],
    "previous_solution": "STEP 1. 곡선 $y=a^{x-4}$와 직선 $y=4$의 교점 A를 구한다. $a^{x-4}=4$에서 $x-4=\\log_a 4=2\\log_a 2$이므로 $A=(4+2\\log_a 2,\\;4)$이다.\n\nSTEP 2. 곡선 $y=\\log_a x$와 직선 $x=4$의 교점 B를 구한다. $y=\\log_a 4=2\\log_a 2$이므로 $B=(4,\\;2\\log_a 2)$이다.\n\nSTEP 3. $t=2\\log_a 2>0$으로 놓으면 $A=(4+t,4)$, $B=(4,t)$이다.\n\nSTEP 4. 점 $A=(4+t,4)$를 직선 $y=x$에 대해 대칭이동한 점은 $(4,4+t)$이고, 수선의 발 C는 A와 대칭점의 중점이므로 $C=\\left(\\frac{8+t}{2},\\frac{8+t}{2}\\right)$이다.\n\nSTEP 5. $AC=\\frac{t}{\\sqrt{2}}$이다.\n\nSTEP 6. 직선 AC는 기울기 $-1$이고 방정식은 $x+y=8+t$이다. 점 $B=(4,t)$에서 이 직선까지의 거리는 $\\frac{|4+t-8-t|}{\\sqrt{2}}=\\frac{4}{\\sqrt{2}}$이다.\n\nSTEP 7. 삼각형 ABC의 넓이는 $\\frac{1}{2}\\times\\frac{t}{\\sqrt{2}}\\times\\frac{4}{\\sqrt{2}}=t=2\\log_a 2$이다.\n\nSTEP 8. $2\\log_a 2=6$에서 $\\log_a 2=3$이고, $a^3=2$에서 $a=2^{1/3}$이다.",
    "previous_clues": "[{\"id\":\"단서A\",\"text\":\"곡선 $y=a^{x-4}$가 직선 $y=4$와 만나는 점을 A라 한다\"},{\"id\":\"단서B\",\"text\":\"곡선 $y=\\\\log_a x$가 직선 $x=4$와 만나는 점을 B라 한다\"},{\"id\":\"단서C\",\"text\":\"점 A에서 직선 $y=x$에 대한 수선의 발을 C라 한다\"},{\"id\":\"단서D\",\"text\":\"$a>1$이다\"},{\"id\":\"단서E\",\"text\":\"삼각형 ABC의 넓이가 6이다\"}]",
    "previous_new_neurons": [],
    "previous_partial_skeleton": [],
    "previous_blockage_point": "",
    "previous_dna_nodes": [
      {
        "id": "top",
        "dna": "Q1",
        "label": "a의 값을 구하라",
        "category": "발문"
      },
      {
        "id": "ask_a",
        "dna": "T1",
        "label": "변수 a",
        "category": "말단"
      },
      {
        "id": "conds",
        "dna": "S1",
        "label": "여러 조건",
        "category": "구조"
      },
      {
        "id": "lim_a",
        "dna": "C2",
        "label": "a > 1",
        "category": "조건"
      },
      {
        "id": "c1_const",
        "dna": "T2",
        "label": "상수 1",
        "category": "말단"
      },
      {
        "id": "crv1",
        "dna": "G2",
        "label": "곡선 y=a^{x-4}",
        "category": "기하"
      },
      {
        "id": "crv1_eq",
        "dna": "C11",
        "label": "곡선1 방정식",
        "category": "조건"
      },
      {
        "id": "crv1_c1",
        "dna": "C1",
        "label": "y=a^{x-4} 등식",
        "category": "조건"
      },
      {
        "id": "crv1_exp",
        "dna": "E4",
        "label": "a^{x-4}",
        "category": "수식"
      },
      {
        "id": "crv1_exponent",
        "dna": "E1",
        "label": "합(x, -4)",
        "category": "수식"
      },
      {
        "id": "vx",
        "dna": "T3",
        "label": "독립변수 x",
        "category": "말단"
      },
      {
        "id": "neg4",
        "dna": "E2",
        "label": "부호반전(4)",
        "category": "수식"
      },
      {
        "id": "c4_const",
        "dna": "T2",
        "label": "상수 4",
        "category": "말단"
      },
      {
        "id": "crv2",
        "dna": "G2",
        "label": "곡선 y=log_a x",
        "category": "기하"
      },
      {
        "id": "crv2_eq",
        "dna": "C11",
        "label": "곡선2 방정식",
        "category": "조건"
      },
      {
        "id": "crv2_c1",
        "dna": "C1",
        "label": "y=log_a x 등식",
        "category": "조건"
      },
      {
        "id": "crv2_log",
        "dna": "E3",
        "label": "log_a x",
        "category": "수식"
      },
      {
        "id": "line_y4",
        "dna": "G12",
        "label": "직선 y=4",
        "category": "기하"
      },
      {
        "id": "line_y4_eq",
        "dna": "C11",
        "label": "직선 y=4 방정식",
        "category": "조건"
      },
      {
        "id": "line_y4_c1",
        "dna": "C1",
        "label": "y=4 등식",
        "category": "조건"
      },
      {
        "id": "line_x4",
        "dna": "G12",
        "label": "직선 x=4",
        "category": "기하"
      },
      {
        "id": "line_x4_eq",
        "dna": "C11",
        "label": "직선 x=4 방정식",
        "category": "조건"
      },
      {
        "id": "line_x4_c1",
        "dna": "C1",
        "label": "x=4 등식",
        "category": "조건"
      },
      {
        "id": "line_yx",
        "dna": "G12",
        "label": "직선 y=x",
        "category": "기하"
      },
      {
        "id": "line_yx_eq",
        "dna": "C11",
        "label": "직선 y=x 방정식",
        "category": "조건"
      },
      {
        "id": "line_yx_c1",
        "dna": "C1",
        "label": "y=x 등식",
        "category": "조건"
      },
      {
        "id": "pt_a",
        "dna": "G1",
        "label": "점 A",
        "category": "기하"
      },
      {
        "id": "meet_a",
        "dna": "C3",
        "label": "crv1과 y=4 교점",
        "category": "조건"
      },
      {
        "id": "pt_b",
        "dna": "G1",
        "label": "점 B",
        "category": "기하"
      },
      {
        "id": "meet_b",
        "dna": "C3",
        "label": "crv2와 x=4 교점",
        "category": "조건"
      },
      {
        "id": "pt_c",
        "dna": "G1",
        "label": "점 C",
        "category": "기하"
      },
      {
        "id": "foot_c",
        "dna": "G27",
        "label": "A에서 y=x 수선발",
        "category": "기하"
      },
      {
        "id": "tri_abc",
        "dna": "G25",
        "label": "삼각형 ABC",
        "category": "기하"
      },
      {
        "id": "area_abc",
        "dna": "G11",
        "label": "삼각형 ABC 넓이",
        "category": "기하"
      },
      {
        "id": "area_cond",
        "dna": "C1",
        "label": "넓이 = 6",
        "category": "조건"
      },
      {
        "id": "c6_const",
        "dna": "T2",
        "label": "상수 6",
        "category": "말단"
      }
    ],
    "previous_dna_edges": [
      {
        "from": "ask_a",
        "to": "top"
      },
      {
        "from": "conds",
        "to": "top"
      },
      {
        "from": "lim_a",
        "to": "ask_a"
      },
      {
        "from": "ask_a",
        "to": "lim_a"
      },
      {
        "from": "c1_const",
        "to": "lim_a"
      },
      {
        "from": "crv1_eq",
        "to": "crv1"
      },
      {
        "from": "crv1_c1",
        "to": "crv1_eq"
      },
      {
        "from": "crv1_exp",
        "to": "crv1_c1"
      },
      {
        "from": "ask_a",
        "to": "crv1_exp"
      },
      {
        "from": "crv1_exponent",
        "to": "crv1_exp"
      },
      {
        "from": "vx",
        "to": "crv1_exponent"
      },
      {
        "from": "neg4",
        "to": "crv1_exponent"
      },
      {
        "from": "c4_const",
        "to": "neg4"
      },
      {
        "from": "crv2_eq",
        "to": "crv2"
      },
      {
        "from": "crv2_c1",
        "to": "crv2_eq"
      },
      {
        "from": "crv2_log",
        "to": "crv2_c1"
      },
      {
        "from": "ask_a",
        "to": "crv2_log"
      },
      {
        "from": "vx",
        "to": "crv2_log"
      },
      {
        "from": "line_y4_eq",
        "to": "line_y4"
      },
      {
        "from": "line_y4_c1",
        "to": "line_y4_eq"
      },
      {
        "from": "c4_const",
        "to": "line_y4_c1"
      },
      {
        "from": "line_x4_eq",
        "to": "line_x4"
      },
      {
        "from": "line_x4_c1",
        "to": "line_x4_eq"
      },
      {
        "from": "c4_const",
        "to": "line_x4_c1"
      },
      {
        "from": "line_yx_eq",
        "to": "line_yx"
      },
      {
        "from": "line_yx_c1",
        "to": "line_yx_eq"
      },
      {
        "from": "vx",
        "to": "line_yx_c1"
      },
      {
        "from": "crv1",
        "to": "meet_a"
      },
      {
        "from": "line_y4",
        "to": "meet_a"
      },
      {
        "from": "pt_a",
        "to": "meet_a"
      },
      {
        "from": "meet_a",
        "to": "conds"
      },
      {
        "from": "crv2",
        "to": "meet_b"
      },
      {
        "from": "line_x4",
        "to": "meet_b"
      },
      {
        "from": "pt_b",
        "to": "meet_b"
      },
      {
        "from": "meet_b",
        "to": "conds"
      },
      {
        "from": "pt_a",
        "to": "foot_c"
      },
      {
        "from": "line_yx",
        "to": "foot_c"
      },
      {
        "from": "pt_c",
        "to": "foot_c"
      },
      {
        "from": "foot_c",
        "to": "conds"
      },
      {
        "from": "pt_a",
        "to": "tri_abc"
      },
      {
        "from": "pt_b",
        "to": "tri_abc"
      },
      {
        "from": "pt_c",
        "to": "tri_abc"
      },
      {
        "from": "tri_abc",
        "to": "area_abc"
      },
      {
        "from": "area_abc",
        "to": "area_cond"
      },
      {
        "from": "c6_const",
        "to": "area_cond"
      },
      {
        "from": "area_cond",
        "to": "conds"
      }
    ],
    "created_at": "2026-03-23T11:39:25.056Z"
  },
  {
    "problem_id": "20(UnknownSource)-로그함수와원의관계",
    "content": "# 20. (Unknown Source) - 로그함수와 원의 관계\n\n## Problem\n\n두 양수 $a$ $(a>1)$, $b$에 대하여 두 곡선 $y=\\log_a(b-1-x)$와 $y=\\log_a(b-x)$의 점근선이 $x$축과 만나는 점을 각각 A, B라 하자. 두 곡선 $y=\\log_a(b-1-x)$와 $y=\\log_a(b-x)$의 점근선이 곡선 $y=(\\sqrt{2})^x$과 만나는 점을 각각 C, D라 할 때, 점 D의 $y$좌표가 점 C의 $y$좌표의 2배이다.\n\n네 점 A, B, C, D가 한 원 위에 있을 때, $a^b$의 값은? [4점]\n\n## Choices\n\n① $2^{\\frac{\\sqrt{2}}{2}}$ ② $2^{\\sqrt{2}}$ ③ $2^{\\frac{3\\sqrt{2}}{2}}$ ④ $2^{2\\sqrt{2}}$ ⑤ $2^{\\frac{5\\sqrt{2}}{2}}$\n\n**Answer**: ③  \n**Difficulty**: unknown  \n**Score**: 4점  \n**Type**: multiple choice\n\n---\n\n## Solution\n\n[FIGURE: 좌표평면에 곡선 $y=\\log_a(b-x)$, 곡선 $y=(\\sqrt{2})^x$, 그리고 점 A, B, C, D와 원이 표시된 그래프]\n\n문제의 조건에 의해\n\n$$\\text{A}(b-1, 0), \\quad \\text{B}(b, 0), \\quad \\text{D}(b, (\\sqrt{2})^b),$$\n\n이고,\n\n점 D의 $y$좌표가 점 C의 $y$좌표의 2배\n\n$$\\Rightarrow (\\text{점 C의 }y\\text{좌표})=\\frac{(\\sqrt{2})^b}{2}=(\\sqrt{2})^{b-2}$$\n\n$$\\Rightarrow \\text{C}(b-2, (\\sqrt{2})^{b-2}) \\quad (\\because \\text{ 점 C는 곡선 } y=(\\sqrt{2})^x \\text{ 위의 점})$$\n\n이다. 이때,\n\n• 네 점 A, B, C, D가 한 원 위에 있음 $\\Rightarrow$ AD가 원의 직경\n\n• $\\angle \\text{ABD}=\\frac{\\pi}{2}$\n\n이므로\n\n$$\\angle \\text{ACD}=\\frac{\\pi}{2} \\Rightarrow (\\text{AC의 기울기})\\times(\\text{CD의 기울기})=-1$$\n\n$$\\Rightarrow \\frac{(\\sqrt{2})^{b-2}-0}{(b-2)-(b-1)} \\times \\frac{(\\sqrt{2})^b-(\\sqrt{2})^{b-2}}{b-(b-2)}=-1$$\n\n$$\\Rightarrow \\frac{-(\\sqrt{2})^{b-2}}{1} \\times \\frac{(\\sqrt{2})^{b-2}(2-1)}{2}=-1$$\n\n$$\\Rightarrow -\\frac{(\\sqrt{2})^{2(b-2)}}{2}=-1$$\n\n$$\\Rightarrow 2^{b-2}=2$$\n\n$$\\Rightarrow b=3$$\n\n을 얻고,\n\n$$\\text{C}(1, \\sqrt{2})\\text{가 }y=\\log_a(3-x) \\text{ 위의 점} \\Rightarrow \\sqrt{2}=\\log_a(2) \\Rightarrow a^{\\sqrt{2}}=2 \\Rightarrow a=2^{\\frac{1}{\\sqrt{2}}}$$\n\n을 얻는다.\n\n$$\\therefore a^b=\\left(2^{\\frac{1}{\\sqrt{2}}}\\right)^3=2^{\\frac{3}{\\sqrt{2}}}=2^{\\frac{3\\sqrt{2}}{2}}$$\n\n---",
    "content_source": "FileLoop",
    "content_length": 1724,
    "skel_status": "ok",
    "dna_status": "dna_missing",
    "needed_neurons": [],
    "needed_dna": [
      {
        "id": "G27",
        "name": "점근선",
        "signature": "(곡선) → 직선",
        "reason": "수직/수평 점근선을 명시적으로 표현하는 DNA가 목록에 없음. G12(직선)로 결과를 표현할 수 있으나 '점근선'이라는 관계 자체를 나타내는 노드가 필요함"
      },
      {
        "id": "G28",
        "name": "공원점",
        "signature": "(점1, 점2, 점3, 점4) → 조건",
        "reason": "네 점이 한 원 위에 있다는 조건(공원/공통원)을 표현하는 DNA가 없음. G9(원)과 G3(위의 점)의 조합으로 표현 가능하나 '한 원 위에 있다'는 단일 관계 조건으로 묶는 구조가 필요"
      }
    ],
    "previous_analysis": "로그함수 두 개의 점근선(수직선)이 x축 및 지수함수와 만드는 네 점이 원에 내접하는 조건을 이용하는 문제. 탈레스 정리로 직각 조건을 세우고 기울기 곱=-1로 b를 결정한 후, 곡선 위의 점 조건으로 a를 결정한다.",
    "previous_matching": "1. 로그함수의 점근선 위치(진수=0) → 사실59(로그 정의 조건에서 진수=0인 x가 점근선)\n2. 점근선이 x축과 만나는 점 A, B 좌표 → 사실59에서 도출된 x값에 y=0 대입\n3. 점근선이 y=(√2)^x과 만나는 점 C, D 좌표 → 전략25(대입 확인)\n4. D의 y좌표가 C의 y좌표의 2배 조건 → 연산18(지수 덧셈법칙으로 (√2)^b/2 = (√2)^{b-2} 정리)\n5. C의 x좌표가 b-2 → 연산2(로그-지수 역함수 관계로 x좌표 결정)\n6. BD⊥AB (B,D가 같은 x좌표) → 사실69(x축 위의 점과 수직선 위의 점)\n7. ∠ABD=π/2이고 네 점이 원 위 → AD가 지름 → 사실11(탈레스 정리)\n8. ∠ACD=π/2 → 사실11\n9. AC기울기×CD기울기=-1 → 사실15(수직 조건)\n10. 기울기 계산 → 연산10\n11. (√2)^{2(b-2)}=2 풀기 → 연산4, 연산2\n12. b=3 대입하여 a 결정 → 전략25, 연산2\n13. a^b 계산 → 연산4, 전략2",
    "previous_matched": [
      "사실59",
      "전략25",
      "연산18",
      "연산2",
      "사실69",
      "사실11",
      "사실15",
      "연산10",
      "전략2",
      "연산4"
    ],
    "previous_skeleton": [
      {
        "from": "단서A",
        "to": "note1",
        "neuron": "사실59",
        "note": "$y=\\log_a(b-1-x)$의 점근선은 $b-1-x=0$, 즉 $x=b-1$이다",
        "step": 1
      },
      {
        "from": "단서A",
        "to": "note2",
        "neuron": "사실59",
        "note": "$y=\\log_a(b-x)$의 점근선은 $b-x=0$, 즉 $x=b$이다",
        "step": 1
      },
      {
        "from": "note1",
        "to": "note3",
        "neuron": "전략25",
        "note": "점근선 $x=b-1$이 $x$축과 만나는 점은 $A(b-1,\\,0)$이다",
        "step": 1
      },
      {
        "from": "note2",
        "to": "note4",
        "neuron": "전략25",
        "note": "점근선 $x=b$가 $x$축과 만나는 점은 $B(b,\\,0)$이다",
        "step": 1
      },
      {
        "from": [
          "note1",
          "단서B"
        ],
        "to": "note5",
        "neuron": "전략25",
        "note": "점근선 $x=b-1$이 $y=(\\sqrt{2})^x$과 만나는 점은 $C(b-1,\\,(\\sqrt{2})^{b-1})$이다",
        "step": 1
      },
      {
        "from": [
          "note2",
          "단서B"
        ],
        "to": "note6",
        "neuron": "전략25",
        "note": "점근선 $x=b$가 $y=(\\sqrt{2})^x$과 만나는 점은 $D(b,\\,(\\sqrt{2})^b)$이다",
        "step": 1
      },
      {
        "from": [
          "단서C",
          "note5",
          "note6"
        ],
        "to": "note7",
        "neuron": "전략2",
        "note": "$(\\sqrt{2})^b = 2 \\cdot (\\sqrt{2})^{b-1}$이다",
        "step": 2
      },
      {
        "from": "note7",
        "to": "note8",
        "neuron": "연산18",
        "note": "$(\\sqrt{2})^b = (\\sqrt{2})^{b-1} \\cdot (\\sqrt{2})^1$이므로 $(\\sqrt{2})^1 = 2$이다",
        "main": false,
        "step": 2
      },
      {
        "from": "note8",
        "to": "note9",
        "neuron": "전략23",
        "note": "$(\\sqrt{2})^1 = \\sqrt{2} \\neq 2$이므로 모순이다. C와 D가 문제 설정대로 각각 다른 점근선 위에 있어야 한다",
        "main": false,
        "step": 2
      },
      {
        "from": [
          "단서C",
          "note6"
        ],
        "to": "note10",
        "neuron": "전략25",
        "note": "C의 $y$좌표는 $(\\sqrt{2})^b / 2$이다",
        "step": 2
      },
      {
        "from": "note10",
        "to": "note11",
        "neuron": "연산18",
        "note": "$(\\sqrt{2})^b / 2 = (\\sqrt{2})^b \\cdot (\\sqrt{2})^{-2} = (\\sqrt{2})^{b-2}$이다",
        "step": 2
      },
      {
        "from": [
          "note11",
          "단서B"
        ],
        "to": "note12",
        "neuron": "연산2",
        "note": "$(\\sqrt{2})^x = (\\sqrt{2})^{b-2}$에서 $x = b-2$이다",
        "step": 2
      },
      {
        "from": [
          "note12",
          "note1"
        ],
        "to": "note13",
        "neuron": "전략2",
        "note": "C는 점근선 $x=b-1$ 위이므로 $b-2 = b-1$이면 모순이다. C는 $y=(\\sqrt{2})^x$ 위의 점이므로 $C(b-2,\\,(\\sqrt{2})^{b-2})$이다",
        "main": false,
        "step": 2
      },
      {
        "from": "note12",
        "to": "note14",
        "neuron": "전략25",
        "note": "$C(b-2,\\,(\\sqrt{2})^{b-2})$이다",
        "step": 2
      },
      {
        "from": [
          "note4",
          "note6"
        ],
        "to": "note15",
        "neuron": "사실69",
        "note": "$B(b,0)$와 $D(b,(\\sqrt{2})^b)$는 같은 $x$좌표를 가지므로 $BD$는 $y$축에 평행하고, $AB$는 $x$축 위이므로 $\\angle ABD = \\pi/2$이다",
        "step": 3
      },
      {
        "from": [
          "note15",
          "단서D"
        ],
        "to": "note16",
        "neuron": "사실11",
        "note": "네 점이 한 원 위에 있고 $\\angle ABD = \\pi/2$이므로 $AD$가 원의 지름이다",
        "step": 3
      },
      {
        "from": [
          "note16",
          "단서D"
        ],
        "to": "note17",
        "neuron": "사실11",
        "note": "$AD$가 지름이고 $C$도 원 위에 있으므로 $\\angle ACD = \\pi/2$이다",
        "step": 4
      },
      {
        "from": "note17",
        "to": "note18",
        "neuron": "사실15",
        "note": "$\\overrightarrow{CA}$와 $\\overrightarrow{CD}$가 수직이므로 기울기의 곱이 $-1$이다",
        "step": 4
      },
      {
        "from": [
          "note3",
          "note14"
        ],
        "to": "note19",
        "neuron": "연산10",
        "note": "AC의 기울기는 $\\frac{0-(\\sqrt{2})^{b-2}}{(b-1)-(b-2)} = -(\\sqrt{2})^{b-2}$이다",
        "step": 5
      },
      {
        "from": [
          "note6",
          "note14"
        ],
        "to": "note20",
        "neuron": "연산10",
        "note": "CD의 기울기는 $\\frac{(\\sqrt{2})^b-(\\sqrt{2})^{b-2}}{b-(b-2)} = \\frac{(\\sqrt{2})^{b-2}((\\sqrt{2})^2-1)}{2} = \\frac{(\\sqrt{2})^{b-2}}{2}$이다",
        "step": 5
      },
      {
        "from": [
          "note18",
          "note19",
          "note20"
        ],
        "to": "note21",
        "neuron": "전략2",
        "note": "$-(\\sqrt{2})^{b-2} \\cdot \\frac{(\\sqrt{2})^{b-2}}{2} = -1$, 즉 $\\frac{((\\sqrt{2})^{b-2})^2}{2}=1$이다",
        "step": 5
      },
      {
        "from": "note21",
        "to": "note22",
        "neuron": "연산4",
        "note": "$((\\sqrt{2})^{b-2})^2 = (\\sqrt{2})^{2(b-2)} = 2^{b-2} = 2$이다",
        "step": 5
      },
      {
        "from": "note22",
        "to": "note23",
        "neuron": "연산2",
        "note": "$b-2=1$이므로 $b=3$이다",
        "step": 5
      },
      {
        "from": [
          "note23",
          "note14"
        ],
        "to": "note24",
        "neuron": "전략25",
        "note": "$b=3$을 대입하면 $A(2,0)$, $B(3,0)$, $C(1,\\sqrt{2})$, $D(3,2\\sqrt{2})$이다",
        "step": 6
      },
      {
        "from": [
          "note24",
          "단서A"
        ],
        "to": "note25",
        "neuron": "전략25",
        "note": "$C(1,\\sqrt{2})$는 곡선 $y=\\log_a(b-1-x)$의 점근선 $x=b-1=2$ 위의 점이 아니라, 곡선 $y=(\\sqrt{2})^x$ 위의 점이다. 점근선 $x=b-1=2$가 $y=(\\sqrt{2})^x$과 만나는 점이 $C$이므로 $C(2, (\\sqrt{2})^2)=(2,2)$가 되어야 한다",
        "main": false,
        "step": 6
      },
      {
        "from": "note24",
        "to": "note26",
        "neuron": "전략25",
        "note": "$C(1,\\sqrt{2})$가 곡선 $y=\\log_a(b-x)$ 위에 있으므로 $\\sqrt{2}=\\log_a(3-1)=\\log_a 2$이다",
        "main": false,
        "step": 6
      },
      {
        "from": [
          "note23",
          "단서A"
        ],
        "to": "note27",
        "neuron": "전략25",
        "note": "$b=3$이면 두 점근선은 $x=2$와 $x=3$이다",
        "step": 6
      },
      {
        "from": [
          "note27",
          "단서B"
        ],
        "to": "note28",
        "neuron": "전략25",
        "note": "점근선 $x=2$가 $y=(\\sqrt{2})^x$과 만나는 점은 $C(2,\\,2)$이고, 점근선 $x=3$이 $y=(\\sqrt{2})^x$과 만나는 점은 $D(3,\\,2\\sqrt{2})$이다",
        "step": 6
      },
      {
        "from": "note28",
        "to": "note29",
        "neuron": "전략25",
        "note": "D의 $y$좌표 $2\\sqrt{2}$가 C의 $y$좌표 $2$의 $\\sqrt{2}$배이므로 2배 조건을 다시 확인한다",
        "main": false,
        "step": 6
      },
      {
        "from": [
          "note3",
          "note28"
        ],
        "to": "note30",
        "neuron": "연산10",
        "note": "AC의 기울기는 $\\frac{2-0}{2-(b-1)}$이다. $b=3$이면 $\\frac{2}{2-2}$으로 분모가 0이다",
        "main": false,
        "step": 6
      },
      {
        "from": "note30",
        "to": "note31",
        "neuron": "전략23",
        "note": "$A$와 $C$의 $x$좌표가 동일하면 $AC$는 수직선으로 $\\angle ACD=\\pi/2$ 조건에서 $CD$는 수평선이어야 한다. $C(2,2)$, $D(3,2\\sqrt{2})$에서 $y$좌표가 다르므로 모순이다",
        "main": false,
        "step": 6
      },
      {
        "from": "note31",
        "to": "note32",
        "neuron": "전략25",
        "note": "문제를 재해석하면 C는 점근선 $x=b-1$ 위가 아니라, 두 곡선 자체가 $y=(\\sqrt{2})^x$과 만나는 점이다. 즉 $\\log_a(b-1-x) = (\\sqrt{2})^x$과 $\\log_a(b-x) = (\\sqrt{2})^x$의 교점으로 해석할 수 있다",
        "main": false,
        "step": 6
      }
    ],
    "previous_solution": "STEP 1. 로그함수의 진수가 0이 되는 조건으로 점근선을 구한다. $y=\\log_a(b-1-x)$의 점근선은 $x=b-1$, $y=\\log_a(b-x)$의 점근선은 $x=b$이다. 점근선이 $x$축과 만나는 점은 $A(b-1,\\,0)$, $B(b,\\,0)$이고, 점근선이 $y=(\\sqrt{2})^x$과 만나는 점은 $C(b-1,\\,(\\sqrt{2})^{b-1})$, $D(b,\\,(\\sqrt{2})^b)$이다.\n\nSTEP 2. D의 $y$좌표가 C의 $y$좌표의 2배이므로 $(\\sqrt{2})^b = 2 \\cdot (\\sqrt{2})^{b-1}$이다. 정리하면 $(\\sqrt{2})^b / (\\sqrt{2})^{b-1} = 2$, 즉 $(\\sqrt{2})^1 = \\sqrt{2} = 2$이므로 모순이다. 따라서 C는 곡선 $y=\\log_a(b-x)$의 점근선이 $y=(\\sqrt{2})^x$과 만나는 점이고, D는 곡선 $y=\\log_a(b-1-x)$의 점근선 — 아니면 문제 문장을 다시 읽으면, 두 곡선의 점근선이 각각 $x=b-1$, $x=b$이고, 이 점근선들이 $x$축과 만나는 점이 A, B이며, $y=(\\sqrt{2})^x$과 만나는 점이 C, D이다. 즉 $C(b-1,\\,(\\sqrt{2})^{b-1})$, $D(b,\\,(\\sqrt{2})^b)$이다. 조건 $(\\sqrt{2})^b = 2(\\sqrt{2})^{b-1}$에서 $\\sqrt{2} = 2$는 불가하므로, C와 D의 대응을 바꾸면: $C(b,\\,(\\sqrt{2})^b)$, $D(b-1,\\,(\\sqrt{2})^{b-1})$으로 놓으면 $(\\sqrt{2})^{b-1} = 2(\\sqrt{2})^b$에서 $(\\sqrt{2})^{-1} = 2$도 불가하다. 원래 풀이대로 C가 $y=(\\sqrt{2})^x$ 위의 별도 점임을 이용한다: D의 $y$좌표 $(\\sqrt{2})^b$의 절반이 C의 $y$좌표 $(\\sqrt{2})^{b-2}$이므로 C의 $x$좌표는 $b-2$이다.\n\nSTEP 3. $B(b,0)$와 $D(b,(\\sqrt{2})^b)$는 같은 $x$좌표를 가지므로 $BD$는 $y$축에 평행하고, $AB$는 $x$축 위이므로 $\\angle ABD = \\pi/2$이다. 네 점이 한 원 위에 있으므로 탈레스 정리의 역에 의해 $AD$가 원의 지름이다.\n\nSTEP 4. $AD$가 지름이고 $C$도 원 위에 있으므로 $\\angle ACD = \\pi/2$이다. 따라서 직선 $CA$와 직선 $CD$의 기울기의 곱이 $-1$이다.\n\nSTEP 5. AC의 기울기는 $\\frac{0-(\\sqrt{2})^{b-2}}{(b-1)-(b-2)} = -(\\sqrt{2})^{b-2}$, CD의 기울기는 $\\frac{(\\sqrt{2})^b-(\\sqrt{2})^{b-2}}{b-(b-2)} = \\frac{(\\sqrt{2})^{b-2}}{2}$이다. 기울기의 곱이 $-1$이므로 $\\frac{((\\sqrt{2})^{b-2})^2}{2}=1$, 즉 $2^{b-2}=2$에서 $b=3$이다.\n\nSTEP 6. $b=3$을 대입하면 $A(2,0)$, $B(3,0)$, $C(1,\\sqrt{2})$, $D(3,2\\sqrt{2})$이다. $C(1,\\sqrt{2})$가 곡선 $y=\\log_a(b-x)=\\log_a(3-x)$ 위의 점이므로 $\\sqrt{2}=\\log_a 2$, 즉 $a^{\\sqrt{2}}=2$에서 $a=2^{1/\\sqrt{2}}$이다.\n\nSTEP 7. $a^b = (2^{1/\\sqrt{2}})^3 = 2^{3/\\sqrt{2}} = 2^{3\\sqrt{2}/2}$이다.",
    "previous_clues": "[{\"id\":\"단서A\",\"text\":\"두 곡선 $y=\\\\log_a(b-1-x)$와 $y=\\\\log_a(b-x)$가 주어진다 ($a>1$, $b>0$)\"},{\"id\":\"단서B\",\"text\":\"곡선 $y=(\\\\sqrt{2})^x$이 주어진다\"},{\"id\":\"단서C\",\"text\":\"점 D의 $y$좌표가 점 C의 $y$좌표의 2배이다\"},{\"id\":\"단서D\",\"text\":\"네 점 A, B, C, D가 한 원 위에 있다\"}]",
    "previous_new_neurons": [],
    "previous_partial_skeleton": [],
    "previous_blockage_point": "",
    "previous_dna_nodes": [
      {
        "id": "top",
        "dna": "Q1",
        "label": "값을 구하라",
        "category": "발문"
      },
      {
        "id": "ask_pow",
        "dna": "E7",
        "label": "a^b",
        "category": "수식"
      },
      {
        "id": "va",
        "dna": "T1",
        "label": "변수 a",
        "category": "말단"
      },
      {
        "id": "vb",
        "dna": "T1",
        "label": "변수 b",
        "category": "말단"
      },
      {
        "id": "va_gt1",
        "dna": "C2",
        "label": "a > 1",
        "category": "조건"
      },
      {
        "id": "va_pos",
        "dna": "C2",
        "label": "a 양수",
        "category": "조건"
      },
      {
        "id": "vb_pos",
        "dna": "C2",
        "label": "b 양수",
        "category": "조건"
      },
      {
        "id": "c1_const",
        "dna": "T2",
        "label": "상수 1",
        "category": "말단"
      },
      {
        "id": "c2_const",
        "dna": "T2",
        "label": "상수 2",
        "category": "말단"
      },
      {
        "id": "vx",
        "dna": "T3",
        "label": "독립변수 x",
        "category": "말단"
      },
      {
        "id": "crv1",
        "dna": "G2",
        "label": "곡선1(log)",
        "category": "기하"
      },
      {
        "id": "crv1_eq",
        "dna": "C11",
        "label": "곡선1 방정식",
        "category": "조건"
      },
      {
        "id": "crv1_c1",
        "dna": "C1",
        "label": "y=log_a(b-1-x)",
        "category": "조건"
      },
      {
        "id": "crv1_log",
        "dna": "E3",
        "label": "log_a(b-1-x)",
        "category": "수식"
      },
      {
        "id": "crv1_inner",
        "dna": "E1",
        "label": "b-1-x 합",
        "category": "수식"
      },
      {
        "id": "neg_c1",
        "dna": "E2",
        "label": "부호반전(1)",
        "category": "수식"
      },
      {
        "id": "neg_x1",
        "dna": "E2",
        "label": "부호반전(x)",
        "category": "수식"
      },
      {
        "id": "crv1_bm1",
        "dna": "E1",
        "label": "b+(-1)",
        "category": "수식"
      },
      {
        "id": "crv2",
        "dna": "G2",
        "label": "곡선2(log)",
        "category": "기하"
      },
      {
        "id": "crv2_eq",
        "dna": "C11",
        "label": "곡선2 방정식",
        "category": "조건"
      },
      {
        "id": "crv2_c1",
        "dna": "C1",
        "label": "y=log_a(b-x)",
        "category": "조건"
      },
      {
        "id": "crv2_log",
        "dna": "E3",
        "label": "log_a(b-x)",
        "category": "수식"
      },
      {
        "id": "crv2_inner",
        "dna": "E1",
        "label": "b+(-x)",
        "category": "수식"
      },
      {
        "id": "neg_x2",
        "dna": "E2",
        "label": "부호반전(x)2",
        "category": "수식"
      },
      {
        "id": "crv3",
        "dna": "G2",
        "label": "곡선3(지수)",
        "category": "기하"
      },
      {
        "id": "crv3_eq",
        "dna": "C11",
        "label": "곡선3 방정식",
        "category": "조건"
      },
      {
        "id": "crv3_c1",
        "dna": "C1",
        "label": "y=(√2)^x",
        "category": "조건"
      },
      {
        "id": "crv3_exp",
        "dna": "E4",
        "label": "(√2)^x",
        "category": "수식"
      },
      {
        "id": "sqrt2",
        "dna": "E8",
        "label": "√2",
        "category": "수식"
      },
      {
        "id": "c2_base",
        "dna": "T2",
        "label": "상수 2(근호)",
        "category": "말단"
      },
      {
        "id": "asym1",
        "dna": "G27",
        "label": "곡선1 점근선",
        "category": "기하"
      },
      {
        "id": "asym1_line",
        "dna": "G12",
        "label": "x=b-1 직선",
        "category": "기하"
      },
      {
        "id": "asym1_eq",
        "dna": "C11",
        "label": "점근선1 방정식",
        "category": "조건"
      },
      {
        "id": "asym1_c1",
        "dna": "C1",
        "label": "x=b-1",
        "category": "조건"
      },
      {
        "id": "b_minus1",
        "dna": "E1",
        "label": "b+(-1)",
        "category": "수식"
      },
      {
        "id": "asym2",
        "dna": "G27",
        "label": "곡선2 점근선",
        "category": "기하"
      },
      {
        "id": "asym2_line",
        "dna": "G12",
        "label": "x=b 직선",
        "category": "기하"
      },
      {
        "id": "asym2_eq",
        "dna": "C11",
        "label": "점근선2 방정식",
        "category": "조건"
      },
      {
        "id": "asym2_c1",
        "dna": "C1",
        "label": "x=b",
        "category": "조건"
      },
      {
        "id": "xaxis",
        "dna": "G13",
        "label": "x축",
        "category": "기하"
      },
      {
        "id": "pt_a",
        "dna": "G1",
        "label": "점 A",
        "category": "기하"
      },
      {
        "id": "meet_a",
        "dna": "C3",
        "label": "점근선1∩x축",
        "category": "조건"
      },
      {
        "id": "pt_b",
        "dna": "G1",
        "label": "점 B",
        "category": "기하"
      },
      {
        "id": "meet_b",
        "dna": "C3",
        "label": "점근선2∩x축",
        "category": "조건"
      },
      {
        "id": "pt_c",
        "dna": "G1",
        "label": "점 C",
        "category": "기하"
      },
      {
        "id": "meet_c",
        "dna": "C3",
        "label": "점근선1∩곡선3",
        "category": "조건"
      },
      {
        "id": "pt_d",
        "dna": "G1",
        "label": "점 D",
        "category": "기하"
      },
      {
        "id": "meet_d",
        "dna": "C3",
        "label": "점근선2∩곡선3",
        "category": "조건"
      },
      {
        "id": "yc",
        "dna": "G4",
        "label": "C의 y좌표",
        "category": "기하"
      },
      {
        "id": "yd",
        "dna": "G4",
        "label": "D의 y좌표",
        "category": "기하"
      },
      {
        "id": "yd_eq",
        "dna": "C1",
        "label": "yD=2×yC",
        "category": "조건"
      },
      {
        "id": "two_yc",
        "dna": "E6",
        "label": "2×yC",
        "category": "수식"
      },
      {
        "id": "concyclic",
        "dna": "G28",
        "label": "A,B,C,D 공원",
        "category": "기하"
      }
    ],
    "previous_dna_edges": [
      {
        "from": "ask_pow",
        "to": "top"
      },
      {
        "from": "va",
        "to": "ask_pow"
      },
      {
        "from": "vb",
        "to": "ask_pow"
      },
      {
        "from": "va",
        "to": "va_gt1"
      },
      {
        "from": "va",
        "to": "va_pos"
      },
      {
        "from": "vb",
        "to": "vb_pos"
      },
      {
        "from": "crv1_eq",
        "to": "crv1"
      },
      {
        "from": "crv1_c1",
        "to": "crv1_eq"
      },
      {
        "from": "crv1_log",
        "to": "crv1_c1"
      },
      {
        "from": "va",
        "to": "crv1_log"
      },
      {
        "from": "crv1_inner",
        "to": "crv1_log"
      },
      {
        "from": "crv1_bm1",
        "to": "crv1_inner"
      },
      {
        "from": "vb",
        "to": "crv1_bm1"
      },
      {
        "from": "neg_c1",
        "to": "crv1_bm1"
      },
      {
        "from": "c1_const",
        "to": "neg_c1"
      },
      {
        "from": "neg_x1",
        "to": "crv1_inner"
      },
      {
        "from": "vx",
        "to": "neg_x1"
      },
      {
        "from": "crv2_eq",
        "to": "crv2"
      },
      {
        "from": "crv2_c1",
        "to": "crv2_eq"
      },
      {
        "from": "crv2_log",
        "to": "crv2_c1"
      },
      {
        "from": "va",
        "to": "crv2_log"
      },
      {
        "from": "crv2_inner",
        "to": "crv2_log"
      },
      {
        "from": "vb",
        "to": "crv2_inner"
      },
      {
        "from": "neg_x2",
        "to": "crv2_inner"
      },
      {
        "from": "vx",
        "to": "neg_x2"
      },
      {
        "from": "crv3_eq",
        "to": "crv3"
      },
      {
        "from": "crv3_c1",
        "to": "crv3_eq"
      },
      {
        "from": "crv3_exp",
        "to": "crv3_c1"
      },
      {
        "from": "sqrt2",
        "to": "crv3_exp"
      },
      {
        "from": "c2_base",
        "to": "sqrt2"
      },
      {
        "from": "vx",
        "to": "crv3_exp"
      },
      {
        "from": "crv1",
        "to": "asym1"
      },
      {
        "from": "asym1_line",
        "to": "asym1"
      },
      {
        "from": "asym1_eq",
        "to": "asym1_line"
      },
      {
        "from": "asym1_c1",
        "to": "asym1_eq"
      },
      {
        "from": "vx",
        "to": "asym1_c1"
      },
      {
        "from": "b_minus1",
        "to": "asym1_c1"
      },
      {
        "from": "vb",
        "to": "b_minus1"
      },
      {
        "from": "neg_c1",
        "to": "b_minus1"
      },
      {
        "from": "crv2",
        "to": "asym2"
      },
      {
        "from": "asym2_line",
        "to": "asym2"
      },
      {
        "from": "asym2_eq",
        "to": "asym2_line"
      },
      {
        "from": "asym2_c1",
        "to": "asym2_eq"
      },
      {
        "from": "vx",
        "to": "asym2_c1"
      },
      {
        "from": "vb",
        "to": "asym2_c1"
      },
      {
        "from": "asym1_line",
        "to": "meet_a"
      },
      {
        "from": "xaxis",
        "to": "meet_a"
      },
      {
        "from": "pt_a",
        "to": "meet_a"
      },
      {
        "from": "asym2_line",
        "to": "meet_b"
      },
      {
        "from": "xaxis",
        "to": "meet_b"
      },
      {
        "from": "pt_b",
        "to": "meet_b"
      },
      {
        "from": "asym1_line",
        "to": "meet_c"
      },
      {
        "from": "crv3",
        "to": "meet_c"
      },
      {
        "from": "pt_c",
        "to": "meet_c"
      },
      {
        "from": "asym2_line",
        "to": "meet_d"
      },
      {
        "from": "crv3",
        "to": "meet_d"
      },
      {
        "from": "pt_d",
        "to": "meet_d"
      },
      {
        "from": "pt_c",
        "to": "yc"
      },
      {
        "from": "pt_d",
        "to": "yd"
      },
      {
        "from": "yd",
        "to": "yd_eq"
      },
      {
        "from": "two_yc",
        "to": "yd_eq"
      },
      {
        "from": "c2_const",
        "to": "two_yc"
      },
      {
        "from": "yc",
        "to": "two_yc"
      },
      {
        "from": "pt_a",
        "to": "concyclic"
      },
      {
        "from": "pt_b",
        "to": "concyclic"
      },
      {
        "from": "pt_c",
        "to": "concyclic"
      },
      {
        "from": "pt_d",
        "to": "concyclic"
      },
      {
        "from": "meet_a",
        "to": "top"
      },
      {
        "from": "meet_b",
        "to": "top"
      },
      {
        "from": "meet_c",
        "to": "top"
      },
      {
        "from": "meet_d",
        "to": "top"
      },
      {
        "from": "yd_eq",
        "to": "top"
      },
      {
        "from": "concyclic",
        "to": "top"
      },
      {
        "from": "va_gt1",
        "to": "top"
      },
      {
        "from": "va_pos",
        "to": "top"
      },
      {
        "from": "vb_pos",
        "to": "top"
      }
    ],
    "created_at": "2026-03-23T11:43:06.615Z"
  },
  {
    "problem_id": "16(UnknownSource)-지수함수와로그함수의교점",
    "content": "# 16. (Unknown Source) - 지수함수와 로그함수의 교점\n\n## Problem\n\n$1$보다 큰 두 상수 $a$, $b$에 대하여 점 $A(0, a)$를 지나고 $x$축에 평행한 직선이 곡선 $y=b^x$와 만나는 점을 $B$라 하자. 점 $A$를 지나고 기울기가 $1$인 직선이 곡선 $y=b^x$와 제$1$사분면에서 만나는 점을 $C$, 점 $C$를 지나고 기울기가 $-1$인 직선이 곡선 $y=\\log_a x$와 만나는 점을 $D$라 할 때,\n\n직선 $AD$의 기울기가 $-\\frac{1}{4}$이다. 삼각형 $ACD$의 넓이가 삼각형 $ABC$의 넓이의 $10$배일 때, $\\log_a b$의 값은? [4점]\n\n[FIGURE: 좌표평면에서 원점 $O$, 점 $A$는 $y$축 위에 위치하고, 곡선 $y=b^x$와 $y=\\log_a x$가 그려져 있다. 점 $B$는 $A$를 지나는 수평선과 $y=b^x$의 교점, 점 $C$는 $A$를 지나고 기울기 $1$인 직선과 $y=b^x$의 교점, 점 $D$는 $C$를 지나고 기울기 $-1$인 직선과 $y=\\log_a x$의 교점이다.]\n\n## Choices\n① $\\frac{\\sqrt{10}}{4}$  ② $\\frac{\\sqrt{10}}{2}$  ③ $\\frac{3\\sqrt{10}}{4}$  ④ $\\sqrt{10}$  ⑤ $\\frac{5\\sqrt{10}}{4}$\n\n**Answer**: ⑤\n**Difficulty**: unknown\n**Score**: 4점\n**Type**: multiple choice\n\n---\n\n## Solution\n\n① $A(0, a)$\n\n② $AC$의 기울기가 $1$ $\\Rightarrow$ $C(k, a+k)$ $(k>0)$\n\n으로 놓으면\n\n- $CD$의 기울기가 $-1$ ⋯ ③\n- 두 곡선 $y=b^x$, $y=\\log_a x$가 직선 $y=x$에 대하여 대칭\n\n$\\Rightarrow$ 두 점 $C$, $D$는 직선 $y=x$에 대하여 대칭\n\n$\\Rightarrow$ $D(a+k, k)$\n\n이므로\n\n$AD$의 기울기 $= -\\frac{1}{4}$, ① $\\Rightarrow$ $\\frac{k-a}{a+k} = -\\frac{1}{4}$\n\n$\\Rightarrow k = \\frac{3a}{5}$\n\n$\\Rightarrow C\\left(\\frac{3a}{5}, \\frac{8a}{5}\\right)$, $D\\left(\\frac{8a}{5}, \\frac{3a}{5}\\right)$ ⋯ ④\n\n이다. 또한, 문제의 조건에 의해\n\n- 삼각형 $ACD$의 넓이가 삼각형 $ABC$의 넓이의 $10$배\n- 두 직선 $AC$, $CD$가 서로 수직 ($\\because$ ②, ③)\n\n이므로 점 $B$에서 선분 $AC$에 내린 수선의 발을 $H$라 하면\n\n$\\Rightarrow$ $\\overline{BH} = \\frac{1}{10}\\overline{CD} = \\frac{\\sqrt{2}}{10}a$ ($\\because$ ④ $\\Rightarrow$ $\\overline{CD} = \\sqrt{2}a$)\n\n$\\Rightarrow$ $\\overline{AB} = \\frac{a}{5}$ ($\\because$ ② $\\Rightarrow$ $\\angle CAB = \\frac{\\pi}{4}$)\n\n$\\Rightarrow$ $B\\left(\\frac{a}{5}, a\\right)$ ($\\because$ ① ⋯ ⓐ\n\n위를 알 수 있다.\n\n따라서\n\n- 점 $B$는 곡선 $y=b^x$ 위의 점, ⓐ $\\Rightarrow$ $b^{\\frac{a}{5}} = a$ ⋯ ⓑ\n- 점 $C$는 곡선 $y=b^x$ 위의 점, ④ $\\Rightarrow$ $b^{\\frac{3a}{5}} = \\frac{8}{5}a$\n\n이므로 두 식을 연립하면\n\n$a^3 = \\frac{8}{5}a$ $\\Rightarrow$ $a = \\frac{2\\sqrt{2}}{\\sqrt{5}}$ ($\\because$ $a>1$)\n\n$\\Rightarrow$ $\\log_a b = \\frac{5}{a} = \\frac{5\\sqrt{10}}{4}$ ($\\because$ ⓑ)\n\n을 얻는다.\n\n---",
    "content_source": "FileLoop",
    "content_length": 2022,
    "skel_status": "neuron_missing",
    "dna_status": "ok",
    "needed_neurons": [
      "???"
    ],
    "needed_dna": [],
    "previous_analysis": "",
    "previous_matching": "",
    "previous_matched": [],
    "previous_skeleton": [],
    "previous_solution": "",
    "previous_clues": "[]",
    "previous_new_neurons": [
      {
        "id": "???",
        "type": "???",
        "statement": "JSON 파싱 실패 — Claude 응답을 파싱할 수 없음",
        "reason": "JSON 파싱 실패",
        "blocked_edge": "N/A"
      }
    ],
    "previous_partial_skeleton": [],
    "previous_blockage_point": "JSON 파싱 실패. Raw 응답 앞 200자: I need to carefully analyze this problem and match each logical step to neurons.\n\n## STEP 1: Problem Analysis\n\nThe problem involves points on exponential and logarithmic curves with geometric conditio",
    "previous_dna_nodes": [
      {
        "id": "top",
        "dna": "Q1",
        "label": "log_a(b) 값",
        "category": "발문"
      },
      {
        "id": "ask_log",
        "dna": "E3",
        "label": "log_a(b)",
        "category": "수식"
      },
      {
        "id": "va",
        "dna": "T1",
        "label": "변수 a",
        "category": "말단"
      },
      {
        "id": "vb",
        "dna": "T1",
        "label": "변수 b",
        "category": "말단"
      },
      {
        "id": "c0",
        "dna": "T2",
        "label": "상수 0",
        "category": "말단"
      },
      {
        "id": "c1",
        "dna": "T2",
        "label": "상수 1",
        "category": "말단"
      },
      {
        "id": "cm1",
        "dna": "T2",
        "label": "상수 -1",
        "category": "말단"
      },
      {
        "id": "c14",
        "dna": "T2",
        "label": "상수 -1/4",
        "category": "말단"
      },
      {
        "id": "c10",
        "dna": "T2",
        "label": "상수 10",
        "category": "말단"
      },
      {
        "id": "vx",
        "dna": "T3",
        "label": "독립변수 x",
        "category": "말단"
      },
      {
        "id": "lim_a",
        "dna": "C2",
        "label": "a > 1",
        "category": "조건"
      },
      {
        "id": "lim_b",
        "dna": "C2",
        "label": "b > 1",
        "category": "조건"
      },
      {
        "id": "pt_a",
        "dna": "G1",
        "label": "점 A",
        "category": "기하"
      },
      {
        "id": "pt_b",
        "dna": "G1",
        "label": "점 B",
        "category": "기하"
      },
      {
        "id": "pt_c",
        "dna": "G1",
        "label": "점 C",
        "category": "기하"
      },
      {
        "id": "pt_d",
        "dna": "G1",
        "label": "점 D",
        "category": "기하"
      },
      {
        "id": "coord_a",
        "dna": "G17",
        "label": "A(0,a)",
        "category": "기하"
      },
      {
        "id": "crv_bx",
        "dna": "G2",
        "label": "곡선 y=b^x",
        "category": "기하"
      },
      {
        "id": "crv_bx_eq",
        "dna": "C11",
        "label": "y=b^x 방정식",
        "category": "조건"
      },
      {
        "id": "crv_bx_c1",
        "dna": "C1",
        "label": "y = b^x",
        "category": "조건"
      },
      {
        "id": "expr_bx",
        "dna": "E4",
        "label": "b^x",
        "category": "수식"
      },
      {
        "id": "crv_loga",
        "dna": "G2",
        "label": "곡선 y=log_ax",
        "category": "기하"
      },
      {
        "id": "crv_loga_eq",
        "dna": "C11",
        "label": "y=log_ax 방정식",
        "category": "조건"
      },
      {
        "id": "crv_loga_c1",
        "dna": "C1",
        "label": "y = log_a(x)",
        "category": "조건"
      },
      {
        "id": "expr_loga",
        "dna": "E3",
        "label": "log_a(x)",
        "category": "수식"
      },
      {
        "id": "line_ab",
        "dna": "G12",
        "label": "직선 AB(수평)",
        "category": "기하"
      },
      {
        "id": "line_ab_par",
        "dna": "G19",
        "label": "x축에 평행",
        "category": "기하"
      },
      {
        "id": "line_ab_pass",
        "dna": "G16",
        "label": "A를 지남",
        "category": "기하"
      },
      {
        "id": "meet_b",
        "dna": "C3",
        "label": "AB선과 b^x 교점",
        "category": "조건"
      },
      {
        "id": "line_ac",
        "dna": "G12",
        "label": "직선 AC(기울기1)",
        "category": "기하"
      },
      {
        "id": "slope_ac_eq",
        "dna": "C1",
        "label": "기울기=1",
        "category": "조건"
      },
      {
        "id": "slope_ac_val",
        "dna": "G5",
        "label": "기울기(A,C)",
        "category": "기하"
      },
      {
        "id": "line_ac_pass",
        "dna": "G16",
        "label": "A를 지남(AC)",
        "category": "기하"
      },
      {
        "id": "meet_c",
        "dna": "C3",
        "label": "AC선과 b^x 교점",
        "category": "조건"
      },
      {
        "id": "q1_cond",
        "dna": "L1",
        "label": "제1사분면",
        "category": "제한"
      },
      {
        "id": "line_cd",
        "dna": "G12",
        "label": "직선 CD(기울기-1)",
        "category": "기하"
      },
      {
        "id": "slope_cd_eq",
        "dna": "C1",
        "label": "기울기=-1",
        "category": "조건"
      },
      {
        "id": "slope_cd_val",
        "dna": "G5",
        "label": "기울기(C,D)",
        "category": "기하"
      },
      {
        "id": "line_cd_pass",
        "dna": "G16",
        "label": "C를 지남(CD)",
        "category": "기하"
      },
      {
        "id": "meet_d",
        "dna": "C3",
        "label": "CD선과 log_a 교점",
        "category": "조건"
      },
      {
        "id": "slope_ad_val",
        "dna": "G5",
        "label": "기울기(A,D)",
        "category": "기하"
      },
      {
        "id": "slope_ad_eq",
        "dna": "C1",
        "label": "기울기AD=-1/4",
        "category": "조건"
      },
      {
        "id": "tri_acd",
        "dna": "G25",
        "label": "삼각형 ACD",
        "category": "기하"
      },
      {
        "id": "tri_abc",
        "dna": "G25",
        "label": "삼각형 ABC",
        "category": "기하"
      },
      {
        "id": "area_acd",
        "dna": "G11",
        "label": "넓이(ACD)",
        "category": "기하"
      },
      {
        "id": "area_abc",
        "dna": "G11",
        "label": "넓이(ABC)",
        "category": "기하"
      },
      {
        "id": "area_10x",
        "dna": "E6",
        "label": "10×넓이(ABC)",
        "category": "수식"
      },
      {
        "id": "area_eq",
        "dna": "C1",
        "label": "넓이ACD=10×ABC",
        "category": "조건"
      },
      {
        "id": "conds",
        "dna": "S1",
        "label": "전체 조건",
        "category": "구조"
      }
    ],
    "previous_dna_edges": [
      {
        "from": "ask_log",
        "to": "top"
      },
      {
        "from": "va",
        "to": "ask_log"
      },
      {
        "from": "vb",
        "to": "ask_log"
      },
      {
        "from": "va",
        "to": "lim_a"
      },
      {
        "from": "c1",
        "to": "lim_a"
      },
      {
        "from": "vb",
        "to": "lim_b"
      },
      {
        "from": "c1",
        "to": "lim_b"
      },
      {
        "from": "c0",
        "to": "coord_a"
      },
      {
        "from": "va",
        "to": "coord_a"
      },
      {
        "from": "coord_a",
        "to": "pt_a"
      },
      {
        "from": "vb",
        "to": "expr_bx"
      },
      {
        "from": "vx",
        "to": "expr_bx"
      },
      {
        "from": "expr_bx",
        "to": "crv_bx_c1"
      },
      {
        "from": "crv_bx_c1",
        "to": "crv_bx_eq"
      },
      {
        "from": "crv_bx_eq",
        "to": "crv_bx"
      },
      {
        "from": "va",
        "to": "expr_loga"
      },
      {
        "from": "vx",
        "to": "expr_loga"
      },
      {
        "from": "expr_loga",
        "to": "crv_loga_c1"
      },
      {
        "from": "crv_loga_c1",
        "to": "crv_loga_eq"
      },
      {
        "from": "crv_loga_eq",
        "to": "crv_loga"
      },
      {
        "from": "pt_a",
        "to": "line_ab_pass"
      },
      {
        "from": "line_ab_pass",
        "to": "line_ab"
      },
      {
        "from": "line_ab_par",
        "to": "line_ab"
      },
      {
        "from": "line_ab",
        "to": "meet_b"
      },
      {
        "from": "crv_bx",
        "to": "meet_b"
      },
      {
        "from": "pt_b",
        "to": "meet_b"
      },
      {
        "from": "pt_a",
        "to": "line_ac_pass"
      },
      {
        "from": "line_ac_pass",
        "to": "line_ac"
      },
      {
        "from": "slope_ac_val",
        "to": "slope_ac_eq"
      },
      {
        "from": "c1",
        "to": "slope_ac_eq"
      },
      {
        "from": "slope_ac_eq",
        "to": "line_ac"
      },
      {
        "from": "pt_a",
        "to": "slope_ac_val"
      },
      {
        "from": "pt_c",
        "to": "slope_ac_val"
      },
      {
        "from": "line_ac",
        "to": "meet_c"
      },
      {
        "from": "crv_bx",
        "to": "meet_c"
      },
      {
        "from": "pt_c",
        "to": "meet_c"
      },
      {
        "from": "q1_cond",
        "to": "meet_c"
      },
      {
        "from": "pt_c",
        "to": "line_cd_pass"
      },
      {
        "from": "line_cd_pass",
        "to": "line_cd"
      },
      {
        "from": "slope_cd_val",
        "to": "slope_cd_eq"
      },
      {
        "from": "cm1",
        "to": "slope_cd_eq"
      },
      {
        "from": "slope_cd_eq",
        "to": "line_cd"
      },
      {
        "from": "pt_c",
        "to": "slope_cd_val"
      },
      {
        "from": "pt_d",
        "to": "slope_cd_val"
      },
      {
        "from": "line_cd",
        "to": "meet_d"
      },
      {
        "from": "crv_loga",
        "to": "meet_d"
      },
      {
        "from": "pt_d",
        "to": "meet_d"
      },
      {
        "from": "pt_a",
        "to": "slope_ad_val"
      },
      {
        "from": "pt_d",
        "to": "slope_ad_val"
      },
      {
        "from": "slope_ad_val",
        "to": "slope_ad_eq"
      },
      {
        "from": "c14",
        "to": "slope_ad_eq"
      },
      {
        "from": "pt_a",
        "to": "tri_acd"
      },
      {
        "from": "pt_c",
        "to": "tri_acd"
      },
      {
        "from": "pt_d",
        "to": "tri_acd"
      },
      {
        "from": "pt_a",
        "to": "tri_abc"
      },
      {
        "from": "pt_b",
        "to": "tri_abc"
      },
      {
        "from": "pt_c",
        "to": "tri_abc"
      },
      {
        "from": "tri_acd",
        "to": "area_acd"
      },
      {
        "from": "tri_abc",
        "to": "area_abc"
      },
      {
        "from": "area_abc",
        "to": "area_10x"
      },
      {
        "from": "c10",
        "to": "area_10x"
      },
      {
        "from": "area_acd",
        "to": "area_eq"
      },
      {
        "from": "area_10x",
        "to": "area_eq"
      },
      {
        "from": "meet_b",
        "to": "conds"
      },
      {
        "from": "meet_c",
        "to": "conds"
      },
      {
        "from": "meet_d",
        "to": "conds"
      },
      {
        "from": "slope_ad_eq",
        "to": "conds"
      },
      {
        "from": "area_eq",
        "to": "conds"
      },
      {
        "from": "conds",
        "to": "top"
      }
    ],
    "created_at": "2026-03-23T11:47:04.595Z"
  },
  {
    "problem_id": "15(UnknownSource)-n제곱근과자연수조건",
    "content": "# 15. (Unknown Source) - n제곱근과 자연수 조건\n\n## Problem\n\n$2 \\leq n \\leq 50$인 자연수 $n$에 대하여 $-\\sqrt[5]{4}$이 어떤 자연수의 $n$제곱근이 되도록 하는 모든 $n$의 값의 합은? [4점]\n\n## Choices\n① 130  ② 140  ③ 150  ④ 160  ⑤ 170\n\n**Answer**: ③\n**Difficulty**: unknown\n**Score**: 4점\n**Type**: multiple choice\n\n---\n\n## Solution\n\n문제에서의 어떤 자연수를 $a$라 하면\n\n$a > 0 \\Rightarrow a$의 $n$제곱근은 $\\begin{cases} \\bullet\\, n\\text{이 홀수이면 } a^{\\frac{1}{n}}\\, (> 0) \\\\ \\bullet\\, n\\text{이 짝수이면 } \\pm a^{\\frac{1}{n}} \\end{cases}$\n\n이므로\n\n$-\\sqrt[5]{4}$이 $a$의 $n$제곱근 $\\Rightarrow \\begin{cases} \\text{① } n\\text{은 짝수 } (\\because -\\sqrt[5]{4} < 0) \\\\ \\text{② } -\\sqrt[5]{4} = -a^{\\frac{1}{n}} \\end{cases}$\n\n임을 알 수 있다.\n\n따라서\n\n② $\\Rightarrow a = (\\sqrt[5]{4})^n = (2^{\\frac{2}{5}})^n = 2^{\\frac{2n}{5}}$의 값이 자연수\n\n$\\Rightarrow \\frac{2n}{5}$가 정수, 즉 $n$은 5의 배수\n\n$\\Rightarrow n$은 짝수이면서 5의 배수, 즉 10의 배수 ($\\because$ ①)\n\n$\\Rightarrow n = 10, 20, 30, 40, 50$\n\n$\\Rightarrow \\left|\\begin{matrix} 2 \\leq n \\leq 50\\text{인 모든} \\\\ \\text{자연수 } n\\text{의 값의} \\\\ \\text{합} \\end{matrix}\\right| = 10 + 20 + 30 + 40 + 50 = 150$\n\n을 얻는다.\n\n---",
    "content_source": "FileLoop",
    "content_length": 1048,
    "skel_status": "neuron_missing",
    "dna_status": "ok",
    "needed_neurons": [
      "???"
    ],
    "needed_dna": [],
    "previous_analysis": "",
    "previous_matching": "",
    "previous_matched": [],
    "previous_skeleton": [],
    "previous_solution": "",
    "previous_clues": "[]",
    "previous_new_neurons": [
      {
        "id": "???",
        "type": "???",
        "statement": "JSON 파싱 실패 — Claude 응답을 파싱할 수 없음",
        "reason": "JSON 파싱 실패",
        "blocked_edge": "N/A"
      }
    ],
    "previous_partial_skeleton": [],
    "previous_blockage_point": "JSON 파싱 실패. Raw 응답 앞 200자: I need to work through this problem carefully, matching each logical step to neurons.\n\n## STEP 1: Problem identification\n- Finding all n (2≤n≤50) such that $-\\sqrt[5]{4}$ is an n-th root of some natur",
    "previous_dna_nodes": [
      {
        "id": "top",
        "dna": "Q3",
        "label": "모든 n의 합",
        "category": "발문"
      },
      {
        "id": "vn",
        "dna": "T1",
        "label": "변수 n",
        "category": "말단"
      },
      {
        "id": "lim_range",
        "dna": "L2",
        "label": "2≤n≤50",
        "category": "제한"
      },
      {
        "id": "lim_nat",
        "dna": "L3",
        "label": "n은 자연수",
        "category": "제한"
      },
      {
        "id": "c2",
        "dna": "T2",
        "label": "상수 2",
        "category": "말단"
      },
      {
        "id": "c50",
        "dna": "T2",
        "label": "상수 50",
        "category": "말단"
      },
      {
        "id": "exist_cond",
        "dna": "X5",
        "label": "자연수 a 존재",
        "category": "존재"
      },
      {
        "id": "va",
        "dna": "T1",
        "label": "변수 a",
        "category": "말단"
      },
      {
        "id": "lim_a_nat",
        "dna": "L3",
        "label": "a는 자연수",
        "category": "제한"
      },
      {
        "id": "nthroot_cond",
        "dna": "C1",
        "label": "n제곱근 등식",
        "category": "조건"
      },
      {
        "id": "nthroot_val",
        "dna": "F7",
        "label": "a의 n제곱근",
        "category": "함수"
      },
      {
        "id": "neg_5root4",
        "dna": "E2",
        "label": "-⁵√4",
        "category": "수식"
      },
      {
        "id": "fifth_root4",
        "dna": "E8",
        "label": "⁵√4",
        "category": "수식"
      },
      {
        "id": "c4",
        "dna": "T2",
        "label": "상수 4",
        "category": "말단"
      },
      {
        "id": "c5",
        "dna": "T2",
        "label": "상수 5",
        "category": "말단"
      }
    ],
    "previous_dna_edges": [
      {
        "from": "lim_range",
        "to": "vn"
      },
      {
        "from": "lim_nat",
        "to": "vn"
      },
      {
        "from": "c2",
        "to": "lim_range"
      },
      {
        "from": "c50",
        "to": "lim_range"
      },
      {
        "from": "exist_cond",
        "to": "top"
      },
      {
        "from": "lim_a_nat",
        "to": "va"
      },
      {
        "from": "va",
        "to": "exist_cond"
      },
      {
        "from": "nthroot_cond",
        "to": "exist_cond"
      },
      {
        "from": "vn",
        "to": "exist_cond"
      },
      {
        "from": "nthroot_val",
        "to": "nthroot_cond"
      },
      {
        "from": "neg_5root4",
        "to": "nthroot_cond"
      },
      {
        "from": "va",
        "to": "nthroot_val"
      },
      {
        "from": "vn",
        "to": "nthroot_val"
      },
      {
        "from": "fifth_root4",
        "to": "neg_5root4"
      },
      {
        "from": "c4",
        "to": "fifth_root4"
      },
      {
        "from": "c5",
        "to": "fifth_root4"
      }
    ],
    "created_at": "2026-03-23T11:48:50.758Z"
  },
  {
    "problem_id": "14(SourceUnknown)-함수의연속성과미분가능성",
    "content": "# 14. (Source Unknown) - 함수의 연속성과 미분가능성\n\n## Problem\n\n두 상수 $a(a>1)$, $b$에 대하여 함수 $f(x)$를\n\n$$f(x) = \\begin{cases} a^{x+b} & (a^{x+b} \\leq 2x+5) \\\\ |2x+5| & (a^{x+b} > 2x+5) \\end{cases}$$\n\n라 하자. 양수 $t$에 대하여 $x$에 대한 방정식 $f(x)=t$의 서로 다른 모든 실근의 합을 $g(t)$라 하자. $g(t) \\neq k$ ($k$는 상수)를 만족시키는 모든 양수 $t$의 값의 범위가 $1<t<9$일 때,\n\n$$f(-k)+f(0)$$\n\n의 값을 구하시오. [4점]\n\n## Choices\n① $18$  \n② [해설]\n\n**Answer**: $18$\n**Difficulty**: unknown\n**Score**: 4점\n**Type**: 단답형\n\n---\n\n## Solution\n\n문제의 $f(x)$의 식에서\n\n① $y=a^{x+b}$, $y=2x+5$의 교점이 개수가 1 이하인 경우,\n$f(x) = |2x+5|$\n($\\because$ 모든 실수 $x$에 대하여 $a^{x+b} \\geq 2x+5$)\n\n② $y=a^{x+b}$, $y=2x+5$의 교점이 개수가 2인 경우,\n두 교점의 $x$좌표를 $p$, $q$라 하면\n\n$$f(x) = \\begin{cases} a^{x+b} & (p \\leq x \\leq q) \\\\ |2x+5| & (x < p, \\, x > q) \\end{cases}$$\n\n임을 알 수 있다.\n\n[FIGURE: 두 개의 그래프가 제시됨]\n- ①의 경우: $y=f(x)$가 $x=-\\frac{5}{2}$에서 V자 형태\n- ②의 경우: $y=f(x)$가 두 점 $p$, $q$에서 지수함수와 직선이 만남\n\n한편, 양수 $t$에 대하여\n\n$x$에 (방정식 $f(x)=t$의 모든 실근의 합) 이므로 ①의 경우,\n\n모든 양수 $t$에 대하여 $g(t)=-5$\n\n($\\because$ $y=|2x+5|$는 $x=-\\frac{5}{2}$에 대하여 대칭)\n\n임을 알 수 있고, ②의 경우,\n\n$$\\begin{cases} t \\geq f(q)\\text{일 때 } g(t)=-5 \\\\ f(p)<t<f(q)\\text{일 때 } g(t) \\neq -5 \\end{cases}$$\n\n임을 알 수 있다.\n\n따라서 문제의 조건에서\n\n$$\\begin{cases} g(t) \\neq k \\text{(}k\\text{는 상수)}를 만족시키는 \\\\ \\text{모든 양수 } t \\text{의 값의 범위가 } 1<t<9 \\end{cases}$$\n\n를 만족시키는 경우는 ②의 경우뿐이므로, 이때\n\n$$k=-5$$\n\n를 얻고,\n\n$$\\begin{cases} f(p)=1 \\Rightarrow 2p+5=a^{p+b}=1 \\\\ f(q)=9 \\Rightarrow 2q+5=a^{q+b}=9 \\end{cases}$$\n\n을 얻는다. $\\Rightarrow p=-2$, $q=2$, $a=\\sqrt{3}$, $b=2$\n\n$$\\therefore f(x) = \\begin{cases} (\\sqrt{3})^{x+2} & (-2 \\leq x \\leq 2) \\\\ |2x+5| & (x < -2, \\, x > 2) \\end{cases}$$\n\n$$\\therefore f(-k)+f(0)=f(5)+f(0)=15+3=18$$\n\n---",
    "content_source": "FileLoop",
    "content_length": 1644,
    "skel_status": "neuron_missing",
    "dna_status": "ok",
    "needed_neurons": [
      "???"
    ],
    "needed_dna": [],
    "previous_analysis": "",
    "previous_matching": "",
    "previous_matched": [],
    "previous_skeleton": [],
    "previous_solution": "",
    "previous_clues": "[]",
    "previous_new_neurons": [
      {
        "id": "???",
        "type": "???",
        "statement": "JSON 파싱 실패 — Claude 응답을 파싱할 수 없음",
        "reason": "JSON 파싱 실패",
        "blocked_edge": "N/A"
      }
    ],
    "previous_partial_skeleton": [],
    "previous_blockage_point": "JSON 파싱 실패. Raw 응답 앞 200자: I need to carefully analyze each logical step and match neurons.\n\n## STEP 1: Problem identification\n- Problem about piecewise function, equation roots, and determining constants.\n\n## STEP 2: Neuron ma",
    "previous_dna_nodes": [
      {
        "id": "top",
        "dna": "Q1",
        "label": "값을 구하라",
        "category": "발문"
      },
      {
        "id": "ask",
        "dna": "E1",
        "label": "f(-k)+f(0)",
        "category": "수식"
      },
      {
        "id": "ask_fk",
        "dna": "F3",
        "label": "f(-k) 적용",
        "category": "함수"
      },
      {
        "id": "ask_f0",
        "dna": "F3",
        "label": "f(0) 적용",
        "category": "함수"
      },
      {
        "id": "neg_k",
        "dna": "E2",
        "label": "부호반전 k",
        "category": "수식"
      },
      {
        "id": "c0",
        "dna": "T2",
        "label": "상수 0",
        "category": "말단"
      },
      {
        "id": "va",
        "dna": "T1",
        "label": "변수 a",
        "category": "말단"
      },
      {
        "id": "vb",
        "dna": "T1",
        "label": "변수 b",
        "category": "말단"
      },
      {
        "id": "vk",
        "dna": "T1",
        "label": "변수 k",
        "category": "말단"
      },
      {
        "id": "lim_a",
        "dna": "C2",
        "label": "a > 1",
        "category": "조건"
      },
      {
        "id": "c1_const",
        "dna": "T2",
        "label": "상수 1",
        "category": "말단"
      },
      {
        "id": "vt",
        "dna": "T3",
        "label": "독립변수 t",
        "category": "말단"
      },
      {
        "id": "vx",
        "dna": "T3",
        "label": "독립변수 x",
        "category": "말단"
      },
      {
        "id": "c2_const",
        "dna": "T2",
        "label": "상수 2",
        "category": "말단"
      },
      {
        "id": "c5_const",
        "dna": "T2",
        "label": "상수 5",
        "category": "말단"
      },
      {
        "id": "fx",
        "dna": "F1",
        "label": "조각함수 f(x)",
        "category": "함수"
      },
      {
        "id": "piece1",
        "dna": "F2",
        "label": "조각1: a^(x+b)",
        "category": "함수"
      },
      {
        "id": "piece2",
        "dna": "F2",
        "label": "조각2: |2x+5|",
        "category": "함수"
      },
      {
        "id": "exp_expr",
        "dna": "E4",
        "label": "지수 a^(x+b)",
        "category": "수식"
      },
      {
        "id": "xpb",
        "dna": "E1",
        "label": "x+b",
        "category": "수식"
      },
      {
        "id": "lin_expr",
        "dna": "E1",
        "label": "2x+5",
        "category": "수식"
      },
      {
        "id": "two_x",
        "dna": "E6",
        "label": "2x 곱",
        "category": "수식"
      },
      {
        "id": "abs_lin",
        "dna": "F5",
        "label": "|2x+5|",
        "category": "함수"
      },
      {
        "id": "cond1",
        "dna": "C2",
        "label": "a^(x+b)≤2x+5",
        "category": "조건"
      },
      {
        "id": "cond2",
        "dna": "C2",
        "label": "a^(x+b)>2x+5",
        "category": "조건"
      },
      {
        "id": "gt_def",
        "dna": "F6",
        "label": "g(t) 함수 정의",
        "category": "함수"
      },
      {
        "id": "gt_body",
        "dna": "S1",
        "label": "실근의 합",
        "category": "구조"
      },
      {
        "id": "eq_fxt",
        "dna": "C1",
        "label": "f(x)=t 방정식",
        "category": "조건"
      },
      {
        "id": "fxt_app",
        "dna": "F3",
        "label": "f(x) 적용",
        "category": "함수"
      },
      {
        "id": "t_pos",
        "dna": "C2",
        "label": "t > 0 양수",
        "category": "조건"
      },
      {
        "id": "roots_diff",
        "dna": "C4",
        "label": "서로다른 실근",
        "category": "조건"
      },
      {
        "id": "g_neq_k",
        "dna": "C2",
        "label": "g(t)≠k",
        "category": "조건"
      },
      {
        "id": "gt_app",
        "dna": "F3",
        "label": "g(t) 적용",
        "category": "함수"
      },
      {
        "id": "range_cond",
        "dna": "S1",
        "label": "1<t<9 범위",
        "category": "구조"
      },
      {
        "id": "range_lo",
        "dna": "C2",
        "label": "t > 1",
        "category": "조건"
      },
      {
        "id": "range_hi",
        "dna": "C2",
        "label": "t < 9",
        "category": "조건"
      },
      {
        "id": "c9_const",
        "dna": "T2",
        "label": "상수 9",
        "category": "말단"
      },
      {
        "id": "range_eq",
        "dna": "C1",
        "label": "범위가 1<t<9",
        "category": "조건"
      }
    ],
    "previous_dna_edges": [
      {
        "from": "ask",
        "to": "top"
      },
      {
        "from": "ask_fk",
        "to": "ask"
      },
      {
        "from": "ask_f0",
        "to": "ask"
      },
      {
        "from": "neg_k",
        "to": "ask_fk"
      },
      {
        "from": "vk",
        "to": "neg_k"
      },
      {
        "from": "fx",
        "to": "ask_fk"
      },
      {
        "from": "fx",
        "to": "ask_f0"
      },
      {
        "from": "c0",
        "to": "ask_f0"
      },
      {
        "from": "piece1",
        "to": "fx"
      },
      {
        "from": "piece2",
        "to": "fx"
      },
      {
        "from": "lim_a",
        "to": "fx"
      },
      {
        "from": "exp_expr",
        "to": "piece1"
      },
      {
        "from": "cond1",
        "to": "piece1"
      },
      {
        "from": "abs_lin",
        "to": "piece2"
      },
      {
        "from": "cond2",
        "to": "piece2"
      },
      {
        "from": "va",
        "to": "exp_expr"
      },
      {
        "from": "xpb",
        "to": "exp_expr"
      },
      {
        "from": "vx",
        "to": "xpb"
      },
      {
        "from": "vb",
        "to": "xpb"
      },
      {
        "from": "exp_expr",
        "to": "cond1"
      },
      {
        "from": "lin_expr",
        "to": "cond1"
      },
      {
        "from": "exp_expr",
        "to": "cond2"
      },
      {
        "from": "lin_expr",
        "to": "cond2"
      },
      {
        "from": "two_x",
        "to": "lin_expr"
      },
      {
        "from": "c5_const",
        "to": "lin_expr"
      },
      {
        "from": "c2_const",
        "to": "two_x"
      },
      {
        "from": "vx",
        "to": "two_x"
      },
      {
        "from": "lin_expr",
        "to": "abs_lin"
      },
      {
        "from": "va",
        "to": "lim_a"
      },
      {
        "from": "c1_const",
        "to": "lim_a"
      },
      {
        "from": "gt_body",
        "to": "gt_def"
      },
      {
        "from": "eq_fxt",
        "to": "gt_body"
      },
      {
        "from": "roots_diff",
        "to": "gt_body"
      },
      {
        "from": "fxt_app",
        "to": "eq_fxt"
      },
      {
        "from": "vt",
        "to": "eq_fxt"
      },
      {
        "from": "fx",
        "to": "fxt_app"
      },
      {
        "from": "vx",
        "to": "fxt_app"
      },
      {
        "from": "t_pos",
        "to": "gt_def"
      },
      {
        "from": "vt",
        "to": "t_pos"
      },
      {
        "from": "c0",
        "to": "t_pos"
      },
      {
        "from": "gt_app",
        "to": "g_neq_k"
      },
      {
        "from": "vk",
        "to": "g_neq_k"
      },
      {
        "from": "gt_def",
        "to": "gt_app"
      },
      {
        "from": "vt",
        "to": "gt_app"
      },
      {
        "from": "g_neq_k",
        "to": "range_eq"
      },
      {
        "from": "range_cond",
        "to": "range_eq"
      },
      {
        "from": "range_lo",
        "to": "range_cond"
      },
      {
        "from": "range_hi",
        "to": "range_cond"
      },
      {
        "from": "vt",
        "to": "range_lo"
      },
      {
        "from": "c1_const",
        "to": "range_lo"
      },
      {
        "from": "vt",
        "to": "range_hi"
      },
      {
        "from": "c9_const",
        "to": "range_hi"
      },
      {
        "from": "range_eq",
        "to": "top"
      }
    ],
    "created_at": "2026-03-23T11:51:24.872Z"
  },
  {
    "problem_id": "Problem13",
    "content": "# Problem13. (Unknown Source) - 함수의 개수 세기\n\n## Problem\n\n두 실수 $a(a>1)$, $k(k<0)$에 대하여 함수 $f(x)$를\n\n$$f(x)=\\begin{cases} |a^{x+1}-3a| & (x \\le 1) \\\\ k(x-1)(x-a) & (x>1) \\end{cases}$$\n\n이라 하자. 자연수 $n$에 대하여 $x$에 대한 방정식 $f(x^n)=n$의 서로 다른 실근의 개수를 $g(n)$이라 할 때, $g(14)=5$이다.\n\n$$k+\\sum_{n=1}^{5}g(5n)$$의 값은? [4점]\n\n## Choices\n① $\\frac{121}{9}$  ② $\\frac{130}{9}$  ③ $\\frac{139}{9}$  ④ $\\frac{148}{9}$  ⑤ $\\frac{157}{9}$\n\n**Answer**: ③\n**Difficulty**: unknown\n**Score**: 4점\n**Type**: multiple choice\n\n---\n\n## Solution\n\n먼저 실수 $t$가\n\n$$f(t)=n$$\n\n을 만족시킨다고 가정하면, $n$이 짝수일 때,\n\n$$(x^n=t \\text{인 } x \\text{의 개수})=\\begin{cases} 0 & (t<0 \\text{인 때}) \\\\ 1 & (t=0 \\text{인 때}) \\\\ 2 & (t>0 \\text{인 때}) \\end{cases}$$\n\n이므로 $g(n)$의 정의에 의해\n\n$n$이 짝수일 때, $g(n)=$(①을 만족시키는 각각의 $t$에 대하여 모든 ②의 값의 합)\n\n이다. 따라서 문제의 조건에서\n\n$$g(14)=5 \\Rightarrow \\begin{cases} ① \\;\\; f(t)=14 \\\\ ② \\;\\; f(x)=14 \\text{인 양수 } x \\text{는 } 2 \\text{개만 존재} \\end{cases}$$\n\n임을 알 수 있고,\n\n① $\\Rightarrow a=7$\n\n이므로 ②를 만족시키는 함수 $f(x)$의 그래프는 다음 [그림]과 같다.\n\n[FIGURE: 좌표평면에 $y=f(x)$ 그래프가 그려져 있음. $x=0$에서 출발하여 $x=1$까지 증가하다가 극댓값 21을 지나고, $x=1$ 이후 감소하여 $x=4$에서 극솟값, $x=7$에서 다시 증가. $y=14$ 수평선과 2개의 양수 교점이 표시됨. $y=28$에서 점근선.]\n\n따라서\n\n$$f(4)=k\\times 3 \\times (-3)=-9k \\Rightarrow k=-\\frac{14}{9} \\;\\; (\\because \\;\\; f(4)=14)$$\n\n이다.\n\n한편, $n$이 홀수일 때는\n\n모든 실수 $t$에 대하여, $(x^n=t \\text{인 } x \\text{의 개수})=1$\n\n이므로 $g(n)$의 정의에 의해\n\n$n$이 홀수일 때 : $g(n)=$(①을 만족시키는 $t$의 개수)\n\n와 같다.\n\n따라서 [그림]을 통해\n\n$$g(5)=4, \\; g(10)=8, \\; g(15)=2, \\; g(20)=2, \\; g(25)=1$$\n\n임을 알 수 있다.\n\n$$\\therefore \\;\\; k+\\sum_{n=1}^{5}g(5n)=-\\frac{14}{9}+17=\\frac{139}{9}$$\n\n---",
    "content_source": "FileLoop",
    "content_length": 1549,
    "skel_status": "neuron_missing",
    "dna_status": "ok",
    "needed_neurons": [
      "???"
    ],
    "needed_dna": [],
    "previous_analysis": "",
    "previous_matching": "",
    "previous_matched": [],
    "previous_skeleton": [],
    "previous_solution": "",
    "previous_clues": "[]",
    "previous_new_neurons": [
      {
        "id": "???",
        "type": "???",
        "statement": "JSON 잘림 (max_tokens 초과 추정) — Claude 응답을 파싱할 수 없음",
        "reason": "JSON 잘림 (max_tokens 초과 추정)",
        "blocked_edge": "N/A"
      }
    ],
    "previous_partial_skeleton": [],
    "previous_blockage_point": "JSON 잘림 (max_tokens 초과 추정). Raw 응답 앞 200자: I need to carefully analyze each logical step and match neurons.\n\n## STEP 1: Problem identification\n\nThe problem involves a piecewise function with absolute value and quadratic parts, finding roots th",
    "previous_dna_nodes": [
      {
        "id": "top",
        "dna": "Q1",
        "label": "값을 구하라",
        "category": "발문"
      },
      {
        "id": "ask",
        "dna": "E1",
        "label": "k+시그마합",
        "category": "수식"
      },
      {
        "id": "sigma",
        "dna": "E1",
        "label": "∑g(5n) n=1~5",
        "category": "수식"
      },
      {
        "id": "g5",
        "dna": "F3",
        "label": "g(5)",
        "category": "함수"
      },
      {
        "id": "g10",
        "dna": "F3",
        "label": "g(10)",
        "category": "함수"
      },
      {
        "id": "g15",
        "dna": "F3",
        "label": "g(15)",
        "category": "함수"
      },
      {
        "id": "g20",
        "dna": "F3",
        "label": "g(20)",
        "category": "함수"
      },
      {
        "id": "g25",
        "dna": "F3",
        "label": "g(25)",
        "category": "함수"
      },
      {
        "id": "va",
        "dna": "T1",
        "label": "변수 a",
        "category": "말단"
      },
      {
        "id": "vk",
        "dna": "T1",
        "label": "변수 k",
        "category": "말단"
      },
      {
        "id": "lim_a",
        "dna": "C2",
        "label": "a>1",
        "category": "조건"
      },
      {
        "id": "lim_k",
        "dna": "C2",
        "label": "k<0",
        "category": "조건"
      },
      {
        "id": "c1",
        "dna": "T2",
        "label": "상수 1",
        "category": "말단"
      },
      {
        "id": "c0",
        "dna": "T2",
        "label": "상수 0",
        "category": "말단"
      },
      {
        "id": "c3",
        "dna": "T2",
        "label": "상수 3",
        "category": "말단"
      },
      {
        "id": "c14",
        "dna": "T2",
        "label": "상수 14",
        "category": "말단"
      },
      {
        "id": "vx",
        "dna": "T3",
        "label": "독립변수 x",
        "category": "말단"
      },
      {
        "id": "vn",
        "dna": "T3",
        "label": "독립변수 n",
        "category": "말단"
      },
      {
        "id": "fdef",
        "dna": "F6",
        "label": "f(x) 정의",
        "category": "함수"
      },
      {
        "id": "fpf",
        "dna": "F1",
        "label": "f(x) 조각함수",
        "category": "함수"
      },
      {
        "id": "piece1",
        "dna": "F2",
        "label": "조각1: x≤1",
        "category": "함수"
      },
      {
        "id": "piece2",
        "dna": "F2",
        "label": "조각2: x>1",
        "category": "함수"
      },
      {
        "id": "dom1",
        "dna": "C2",
        "label": "x≤1",
        "category": "조건"
      },
      {
        "id": "dom2",
        "dna": "C2",
        "label": "x>1",
        "category": "조건"
      },
      {
        "id": "expr1",
        "dna": "E5",
        "label": "|a^{x+1}-3a|",
        "category": "수식"
      },
      {
        "id": "inner1",
        "dna": "E1",
        "label": "a^{x+1}-3a",
        "category": "수식"
      },
      {
        "id": "exp1",
        "dna": "E4",
        "label": "a^{x+1}",
        "category": "수식"
      },
      {
        "id": "xp1",
        "dna": "E1",
        "label": "x+1",
        "category": "수식"
      },
      {
        "id": "neg3a",
        "dna": "E2",
        "label": "-(3a)",
        "category": "수식"
      },
      {
        "id": "threeA",
        "dna": "E6",
        "label": "3×a",
        "category": "수식"
      },
      {
        "id": "expr2",
        "dna": "E6",
        "label": "k(x-1)(x-a)",
        "category": "수식"
      },
      {
        "id": "kprod",
        "dna": "E6",
        "label": "k×(x-1)",
        "category": "수식"
      },
      {
        "id": "xm1",
        "dna": "E1",
        "label": "x-1",
        "category": "수식"
      },
      {
        "id": "neg1",
        "dna": "E2",
        "label": "부호반전 1",
        "category": "수식"
      },
      {
        "id": "xma",
        "dna": "E1",
        "label": "x-a",
        "category": "수식"
      },
      {
        "id": "negA",
        "dna": "E2",
        "label": "부호반전 a",
        "category": "수식"
      },
      {
        "id": "gdef",
        "dna": "F6",
        "label": "g(n) 정의",
        "category": "함수"
      },
      {
        "id": "eq_fxn",
        "dna": "C1",
        "label": "f(x^n)=n",
        "category": "조건"
      },
      {
        "id": "fxn_app",
        "dna": "F3",
        "label": "f(x^n)",
        "category": "함수"
      },
      {
        "id": "xpown",
        "dna": "E7",
        "label": "x^n",
        "category": "수식"
      },
      {
        "id": "rootcount",
        "dna": "C9",
        "label": "실근 개수=n",
        "category": "조건"
      },
      {
        "id": "nat_n",
        "dna": "L3",
        "label": "n은 자연수",
        "category": "제한"
      },
      {
        "id": "cond_g14",
        "dna": "C9",
        "label": "g(14)=5",
        "category": "조건"
      },
      {
        "id": "g14app",
        "dna": "F3",
        "label": "g(14)",
        "category": "함수"
      },
      {
        "id": "c5",
        "dna": "T2",
        "label": "상수 5",
        "category": "말단"
      },
      {
        "id": "conds",
        "dna": "S1",
        "label": "조건 묶음",
        "category": "구조"
      }
    ],
    "previous_dna_edges": [
      {
        "from": "ask",
        "to": "top"
      },
      {
        "from": "vk",
        "to": "ask"
      },
      {
        "from": "sigma",
        "to": "ask"
      },
      {
        "from": "g5",
        "to": "sigma"
      },
      {
        "from": "g10",
        "to": "sigma"
      },
      {
        "from": "g15",
        "to": "sigma"
      },
      {
        "from": "g20",
        "to": "sigma"
      },
      {
        "from": "g25",
        "to": "sigma"
      },
      {
        "from": "gdef",
        "to": "g5"
      },
      {
        "from": "gdef",
        "to": "g10"
      },
      {
        "from": "gdef",
        "to": "g15"
      },
      {
        "from": "gdef",
        "to": "g20"
      },
      {
        "from": "gdef",
        "to": "g25"
      },
      {
        "from": "lim_a",
        "to": "va"
      },
      {
        "from": "lim_k",
        "to": "vk"
      },
      {
        "from": "va",
        "to": "lim_a"
      },
      {
        "from": "c1",
        "to": "lim_a"
      },
      {
        "from": "vk",
        "to": "lim_k"
      },
      {
        "from": "c0",
        "to": "lim_k"
      },
      {
        "from": "conds",
        "to": "top"
      },
      {
        "from": "fdef",
        "to": "conds"
      },
      {
        "from": "fpf",
        "to": "fdef"
      },
      {
        "from": "piece1",
        "to": "fpf"
      },
      {
        "from": "piece2",
        "to": "fpf"
      },
      {
        "from": "dom1",
        "to": "piece1"
      },
      {
        "from": "expr1",
        "to": "piece1"
      },
      {
        "from": "dom2",
        "to": "piece2"
      },
      {
        "from": "expr2",
        "to": "piece2"
      },
      {
        "from": "vx",
        "to": "dom1"
      },
      {
        "from": "c1",
        "to": "dom1"
      },
      {
        "from": "vx",
        "to": "dom2"
      },
      {
        "from": "c1",
        "to": "dom2"
      },
      {
        "from": "inner1",
        "to": "expr1"
      },
      {
        "from": "exp1",
        "to": "inner1"
      },
      {
        "from": "neg3a",
        "to": "inner1"
      },
      {
        "from": "va",
        "to": "exp1"
      },
      {
        "from": "xp1",
        "to": "exp1"
      },
      {
        "from": "vx",
        "to": "xp1"
      },
      {
        "from": "c1",
        "to": "xp1"
      },
      {
        "from": "threeA",
        "to": "neg3a"
      },
      {
        "from": "c3",
        "to": "threeA"
      },
      {
        "from": "va",
        "to": "threeA"
      },
      {
        "from": "kprod",
        "to": "expr2"
      },
      {
        "from": "xma",
        "to": "expr2"
      },
      {
        "from": "vk",
        "to": "kprod"
      },
      {
        "from": "xm1",
        "to": "kprod"
      },
      {
        "from": "vx",
        "to": "xm1"
      },
      {
        "from": "neg1",
        "to": "xm1"
      },
      {
        "from": "c1",
        "to": "neg1"
      },
      {
        "from": "vx",
        "to": "xma"
      },
      {
        "from": "negA",
        "to": "xma"
      },
      {
        "from": "va",
        "to": "negA"
      },
      {
        "from": "gdef",
        "to": "conds"
      },
      {
        "from": "eq_fxn",
        "to": "gdef"
      },
      {
        "from": "fxn_app",
        "to": "eq_fxn"
      },
      {
        "from": "vn",
        "to": "eq_fxn"
      },
      {
        "from": "fpf",
        "to": "fxn_app"
      },
      {
        "from": "xpown",
        "to": "fxn_app"
      },
      {
        "from": "vx",
        "to": "xpown"
      },
      {
        "from": "vn",
        "to": "xpown"
      },
      {
        "from": "rootcount",
        "to": "gdef"
      },
      {
        "from": "nat_n",
        "to": "vn"
      },
      {
        "from": "cond_g14",
        "to": "conds"
      },
      {
        "from": "g14app",
        "to": "cond_g14"
      },
      {
        "from": "c14",
        "to": "cond_g14"
      },
      {
        "from": "c5",
        "to": "cond_g14"
      },
      {
        "from": "gdef",
        "to": "g14app"
      },
      {
        "from": "c14",
        "to": "g14app"
      },
      {
        "from": "c5",
        "to": "sigma"
      }
    ],
    "created_at": "2026-03-23T11:55:47.000Z"
  },
  {
    "problem_id": "19(수능/모의고사)-로그방정식의실근의개수",
    "content": "# 19. (수능/모의고사) - 로그 방정식의 실근의 개수\n\n## Problem\n\n상수 $k\\ (k > 4\\sqrt{5})$와 2 이상의 자연수 $n$에 대하여 $x$에 대한 방정식\n\n$$\\frac{\\log_n (x^2-20)^n}{n} = \\frac{\\log_n (2x+k)^{n+1}}{n+1} + 1$$\n\n의 실근의 개수가 3이 되도록 하는 모든 $n$의 값이 $n_1,\\; n_2\\ (n_2 > n_1 \\geq 2)$일 때, $k + n_2 - n_1$의 값은? [4점]\n\n## Choices\n① 10 &emsp; ② 11 &emsp; ③ 12 &emsp; ④ 13 &emsp; ⑤ 14\n\n**Answer**: ①\n**Difficulty**: 상\n**Score**: 4점\n**Type**: multiple choice\n\n---\n\n## Solution\n\n문제의 방정식을 정리하면\n\n**① $n$이 홀수일 때,** $\\log_n(x^2-20) = \\log_n|2x+k| + 1$\n\n$$\\Rightarrow x^2 - 20 = 2n\\left|x+\\frac{k}{2}\\right|,\\quad x^2-20>0,\\quad x \\neq -\\frac{k}{2}$$\n\n**② $n$이 짝수일 때,** $\\log_n|x^2-20| = \\log_n(2x+k) + 1$\n\n$$\\Rightarrow |x^2-20| = 2n\\left(x+\\frac{k}{2}\\right),\\quad x^2 \\neq 20,\\quad x > -\\frac{k}{2}$$\n\n이때, $k > 4\\sqrt{5} \\Rightarrow -\\dfrac{k}{2} < -2\\sqrt{5}$\n\n임을 함께 고려하면 방정식의 실근의 개수가 3이 되는 경우를 다음 그림과 같이 나타낼 수 있다.\n\n[FIGURE: ①의 경우 — $y = x^2 - 20$과 $y = 2n\\left|x + \\frac{k}{2}\\right|$의 그래프가 $x < -2\\sqrt{5}$에서 접하는 그림. ②의 경우 — $y = |x^2 - 20|$과 $y = 2n\\left(x + \\frac{k}{2}\\right)$의 그래프가 $-2\\sqrt{5} < x < 2\\sqrt{5}$에서 접하는 그림.]\n\n**①의 경우:**\n\n$y = x^2 - 20$, $y = -2n\\!\\left(x + \\dfrac{k}{2}\\right)$이 $x < -2\\sqrt{5}$에서 접함\n\n$$\\Rightarrow x^2 + 2nx + kn - 20 = 0 \\text{이 } x < -2\\sqrt{5} \\text{인 중근을 가짐}$$\n\n$$\\Rightarrow \\begin{cases} D/4 = n^2 - kn + 20 = 0 \\cdots \\text{ⓐ} \\\\ \\text{(대칭축)} = -n < -2\\sqrt{5} \\Rightarrow n > 2\\sqrt{5}\\text{인 홀수} \\\\ \\Rightarrow n = 5,\\; 7,\\; \\cdots \\quad \\cdots \\text{ⓑ} \\end{cases}$$\n\n**②의 경우:**\n\n$y = -(x^2-20)$, $y = 2n\\!\\left(x + \\dfrac{k}{2}\\right)$이 $-2\\sqrt{5} < x < 2\\sqrt{5}$에서 접함\n\n$$\\Rightarrow x^2 + 2nx + kn - 20 = 0 \\text{이 } -2\\sqrt{5} < x < 2\\sqrt{5}\\text{인 중근을 가짐}$$\n\n$$\\Rightarrow \\begin{cases} \\text{중근을 가질 조건은 ⓐ과 동일} \\\\ -2\\sqrt{5} < -n < 2\\sqrt{5}\\ (\\because \\text{ⓑ의 과정 참고}) \\\\ \\Rightarrow n \\text{은 } -2\\sqrt{5} < n < 2\\sqrt{5}\\text{인 짝수} \\\\ \\Rightarrow n = 2,\\; 4 \\quad \\cdots \\text{ⓒ} \\end{cases}$$\n\n따라서 문제의 조건과 ⓐ에 의해\n\n$$\\begin{cases} n\\text{에 대한 이차방정식 } n^2 - kn + 20 = 0 \\text{이} \\\\ \\text{서로 다른 두 실근이 } n_1,\\; n_2\\ (n_2 > n_1 \\geq 2) \\end{cases}$$\n\n임을 알 수 있고, 이때\n\n$$n_1 \\times n_2 = 20 \\quad (\\because \\text{근과 계수의 관계})$$\n\n이므로 ⓑ, ⓒ에서\n\n$$n_1 = 4,\\quad n_2 = 5$$\n\n임을 알 수 있고,\n\n$$\\text{ⓐ} \\Rightarrow k = 9$$\n\n를 얻는다.\n\n$$\\therefore\\; k + n_2 - n_1 = 9 + 5 - 4 = \\boxed{10}$$\n\n---",
    "content_source": "FileLoop",
    "content_length": 2274,
    "skel_status": "neuron_missing",
    "dna_status": "ok",
    "needed_neurons": [
      "사실79"
    ],
    "needed_dna": [],
    "previous_analysis": "",
    "previous_matching": "1. n의 홀짝에 따라 경우 분리 → 전략12 (거듭제곱근에서 n 홀짝 경우분리)\n2. 거듭제곱의 부호가 n 홀짝에 따라 달라짐 → 사실76\n3. log_n(A^n)/n 정리에서 지수를 로그 밖으로 → 연산17 (역방향)\n4. 절댓값 처리 → 전략6\n5. 로그함수의 단조성으로 단사 → 사실12 + 사실58\n6. 진수 비교로 방정식 변환 → 사실58 적용 (단사함수이므로 f(a)=f(b)⇒a=b)\n7. 방정식의 근 개수 = 그래프 교점 수 → 전략5\n8. k>4√5에서 -k/2<-2√5 유도 → 연산22\n9. 이차방정식 접선(중근) 조건 D=0 → ❌ 매칭 뉴런 없음 (사실79 필요)\n10. 중근의 x좌표 범위 조건 확인 → 전략25\n11. 근과 계수의 관계 n₁n₂=20 → 사실78\n12. 인수 쌍 전수조사 → 전략17\n13. 각 후보가 ⓑⓒ조건 만족하는지 확인 → 전략25 + 전략20\n14. k=n₁+n₂=9 산출 및 최종 답 계산 → 연산21/전략25",
    "previous_matched": [
      "전략12",
      "사실76",
      "연산17",
      "전략6",
      "사실58",
      "사실12",
      "전략5",
      "연산22",
      "사실78",
      "전략17",
      "전략25",
      "전략20",
      "전략2",
      "연산28",
      "연산21",
      "사실35"
    ],
    "previous_skeleton": [],
    "previous_solution": "",
    "previous_clues": "[{\"id\":\"단서A\",\"text\":\"$\\\\frac{\\\\log_n (x^2-20)^n}{n} = \\\\frac{\\\\log_n (2x+k)^{n+1}}{n+1} + 1$이고 $n$은 2 이상의 자연수이다\"},{\"id\":\"단서B\",\"text\":\"$k > 4\\\\sqrt{5}$이다\"},{\"id\":\"단서C\",\"text\":\"방정식의 실근의 개수가 3이 되도록 하는 모든 $n$의 값이 $n_1,\\\\,n_2$ ($n_2>n_1\\\\geq 2$)뿐이다\"}]",
    "previous_new_neurons": [
      {
        "id": "사실79",
        "type": "fact",
        "statement": "이차방정식 $ax^2+bx+c=0$의 판별식 $D=b^2-4ac$에 대해, $D>0$이면 서로 다른 두 실근, $D=0$이면 중근(정확히 하나의 실근), $D<0$이면 실근이 없다.",
        "reason": "STEP 3·4에서 접선 조건(중근 조건)을 세울 때 판별식 D=0을 사용하는데, 이차방정식의 판별식과 근의 개수 관계를 나타내는 뉴런이 목록에 없다. 사실9는 이차함수의 꼭짓점값 관점이고, 일반 이차방정식의 판별식 조건과는 다르다.",
        "blocked_edge": "note8 → note9 (이차방정식 x²+2nx+(nk-20)=0이 중근을 가질 조건 D/4=n²-nk+20=0을 세우는 단계)"
      }
    ],
    "previous_partial_skeleton": [
      {
        "from": "단서A",
        "to": "note1",
        "neuron": "전략12",
        "note": "$n$의 홀짝에 따라 거듭제곱의 부호 성질이 달라지므로 (i) $n$ 홀수, (ii) $n$ 짝수로 경우를 나눈다",
        "main": true,
        "step": 1
      },
      {
        "from": [
          "단서A",
          "note1"
        ],
        "to": "note2",
        "neuron": "사실76",
        "note": "(i) $n$ 홀수: $(x^2-20)^n>0 \\Leftrightarrow x^2-20>0$, $(2x+k)^{n+1}>0 \\Leftrightarrow 2x+k\\neq 0$이다",
        "main": true,
        "step": 1
      },
      {
        "from": "note2",
        "to": "note3",
        "neuron": "연산17",
        "note": "좌변$=\\log_n(x^2-20)$, 우변 첫 항$=\\log_n|2x+k|$이다",
        "main": true,
        "step": 1
      },
      {
        "from": "note3",
        "to": "note4",
        "neuron": "사실58",
        "note": "(i)의 방정식: $x^2-20 = 2n|x+k/2|$, $x^2>20$, $x\\neq -k/2$이다",
        "main": true,
        "step": 1
      },
      {
        "from": [
          "단서A",
          "note1"
        ],
        "to": "note5",
        "neuron": "사실76",
        "note": "(ii) $n$ 짝수: $(x^2-20)^n>0 \\Leftrightarrow x^2\\neq 20$, $(2x+k)^{n+1}>0 \\Leftrightarrow 2x+k>0$이다",
        "main": true,
        "step": 1
      },
      {
        "from": "note5",
        "to": "note6",
        "neuron": "연산17",
        "note": "좌변$=\\log_n|x^2-20|$, 우변 첫 항$=\\log_n(2x+k)$이다",
        "main": true,
        "step": 1
      },
      {
        "from": "note6",
        "to": "note7",
        "neuron": "사실58",
        "note": "(ii)의 방정식: $|x^2-20|=2n(x+k/2)$, $x^2\\neq 20$, $x>-k/2$이다",
        "main": true,
        "step": 1
      },
      {
        "from": "단서B",
        "to": "note8",
        "neuron": "연산22",
        "note": "$k>4\\sqrt{5}$에서 $-k/2 < -2\\sqrt{5}$이다",
        "main": true,
        "step": 2
      }
    ],
    "previous_blockage_point": "note8에서 각 경우의 이차방정식이 특정 구간에서 중근을 가질 조건(판별식 D=0)을 세우려는데, 이차방정식의 판별식과 근의 개수 관계에 대한 매칭 뉴런이 없음",
    "previous_dna_nodes": [
      {
        "id": "top",
        "dna": "Q1",
        "label": "값을 구하라",
        "category": "발문"
      },
      {
        "id": "ask_sum",
        "dna": "E1",
        "label": "k+n2-n1 합",
        "category": "수식"
      },
      {
        "id": "ask_sub",
        "dna": "E1",
        "label": "n2+(-n1)",
        "category": "수식"
      },
      {
        "id": "neg_n1",
        "dna": "E2",
        "label": "-n1",
        "category": "수식"
      },
      {
        "id": "vk",
        "dna": "T1",
        "label": "변수 k",
        "category": "말단"
      },
      {
        "id": "vn1",
        "dna": "T1",
        "label": "변수 n1",
        "category": "말단"
      },
      {
        "id": "vn2",
        "dna": "T1",
        "label": "변수 n2",
        "category": "말단"
      },
      {
        "id": "vn",
        "dna": "T1",
        "label": "변수 n",
        "category": "말단"
      },
      {
        "id": "vx",
        "dna": "T3",
        "label": "독립변수 x",
        "category": "말단"
      },
      {
        "id": "c1",
        "dna": "T2",
        "label": "상수 1",
        "category": "말단"
      },
      {
        "id": "c20",
        "dna": "T2",
        "label": "상수 20",
        "category": "말단"
      },
      {
        "id": "c2_const",
        "dna": "T2",
        "label": "상수 2",
        "category": "말단"
      },
      {
        "id": "c4rt5",
        "dna": "T2",
        "label": "상수 4√5",
        "category": "말단"
      },
      {
        "id": "c3_cnt",
        "dna": "T2",
        "label": "상수 3",
        "category": "말단"
      },
      {
        "id": "cneg1",
        "dna": "T2",
        "label": "상수 -1",
        "category": "말단"
      },
      {
        "id": "lim_k",
        "dna": "C2",
        "label": "k > 4√5",
        "category": "조건"
      },
      {
        "id": "lim_n_nat",
        "dna": "L3",
        "label": "n은 자연수",
        "category": "제한"
      },
      {
        "id": "lim_n_range",
        "dna": "L2",
        "label": "n ≥ 2",
        "category": "제한"
      },
      {
        "id": "lim_n2n1",
        "dna": "C2",
        "label": "n2>n1≥2",
        "category": "조건"
      },
      {
        "id": "eq_main",
        "dna": "C11",
        "label": "x에 대한 방정식",
        "category": "조건"
      },
      {
        "id": "eq_c1",
        "dna": "C1",
        "label": "좌변=우변",
        "category": "조건"
      },
      {
        "id": "lhs",
        "dna": "E6",
        "label": "좌변(분수)",
        "category": "수식"
      },
      {
        "id": "lhs_log",
        "dna": "E3",
        "label": "log_n((x²-20)^n)",
        "category": "수식"
      },
      {
        "id": "lhs_arg",
        "dna": "E7",
        "label": "(x²-20)^n",
        "category": "수식"
      },
      {
        "id": "x2_minus20",
        "dna": "E1",
        "label": "x²+(-20)",
        "category": "수식"
      },
      {
        "id": "x2",
        "dna": "E7",
        "label": "x²",
        "category": "수식"
      },
      {
        "id": "neg20",
        "dna": "E2",
        "label": "-20",
        "category": "수식"
      },
      {
        "id": "inv_n",
        "dna": "E7",
        "label": "n^(-1)",
        "category": "수식"
      },
      {
        "id": "rhs",
        "dna": "E1",
        "label": "우변(합)",
        "category": "수식"
      },
      {
        "id": "rhs_frac",
        "dna": "E6",
        "label": "우변(분수항)",
        "category": "수식"
      },
      {
        "id": "rhs_log",
        "dna": "E3",
        "label": "log_n((2x+k)^(n+1))",
        "category": "수식"
      },
      {
        "id": "rhs_arg",
        "dna": "E7",
        "label": "(2x+k)^(n+1)",
        "category": "수식"
      },
      {
        "id": "twox_plus_k",
        "dna": "E1",
        "label": "2x+k",
        "category": "수식"
      },
      {
        "id": "twox",
        "dna": "E6",
        "label": "2x",
        "category": "수식"
      },
      {
        "id": "n_plus1",
        "dna": "E1",
        "label": "n+1",
        "category": "수식"
      },
      {
        "id": "inv_n1",
        "dna": "E7",
        "label": "(n+1)^(-1)",
        "category": "수식"
      },
      {
        "id": "root_cnt3",
        "dna": "C9",
        "label": "실근 개수=3",
        "category": "조건"
      },
      {
        "id": "all_n_vals",
        "dna": "C19",
        "label": "모든 n값 n1,n2",
        "category": "조건"
      }
    ],
    "previous_dna_edges": [
      {
        "from": "ask_sum",
        "to": "top"
      },
      {
        "from": "vk",
        "to": "ask_sum"
      },
      {
        "from": "ask_sub",
        "to": "ask_sum"
      },
      {
        "from": "vn2",
        "to": "ask_sub"
      },
      {
        "from": "neg_n1",
        "to": "ask_sub"
      },
      {
        "from": "vn1",
        "to": "neg_n1"
      },
      {
        "from": "lim_k",
        "to": "vk"
      },
      {
        "from": "c4rt5",
        "to": "lim_k"
      },
      {
        "from": "lim_n_nat",
        "to": "vn"
      },
      {
        "from": "lim_n_range",
        "to": "vn"
      },
      {
        "from": "lim_n2n1",
        "to": "top"
      },
      {
        "from": "vn1",
        "to": "lim_n2n1"
      },
      {
        "from": "vn2",
        "to": "lim_n2n1"
      },
      {
        "from": "c2_const",
        "to": "lim_n2n1"
      },
      {
        "from": "eq_main",
        "to": "top"
      },
      {
        "from": "eq_c1",
        "to": "eq_main"
      },
      {
        "from": "lhs",
        "to": "eq_c1"
      },
      {
        "from": "rhs",
        "to": "eq_c1"
      },
      {
        "from": "lhs_log",
        "to": "lhs"
      },
      {
        "from": "inv_n",
        "to": "lhs"
      },
      {
        "from": "vn",
        "to": "inv_n"
      },
      {
        "from": "cneg1",
        "to": "inv_n"
      },
      {
        "from": "vn",
        "to": "lhs_log"
      },
      {
        "from": "lhs_arg",
        "to": "lhs_log"
      },
      {
        "from": "x2_minus20",
        "to": "lhs_arg"
      },
      {
        "from": "vn",
        "to": "lhs_arg"
      },
      {
        "from": "x2",
        "to": "x2_minus20"
      },
      {
        "from": "neg20",
        "to": "x2_minus20"
      },
      {
        "from": "c20",
        "to": "neg20"
      },
      {
        "from": "vx",
        "to": "x2"
      },
      {
        "from": "c2_const",
        "to": "x2"
      },
      {
        "from": "rhs_frac",
        "to": "rhs"
      },
      {
        "from": "c1",
        "to": "rhs"
      },
      {
        "from": "rhs_log",
        "to": "rhs_frac"
      },
      {
        "from": "inv_n1",
        "to": "rhs_frac"
      },
      {
        "from": "n_plus1",
        "to": "inv_n1"
      },
      {
        "from": "cneg1",
        "to": "inv_n1"
      },
      {
        "from": "vn",
        "to": "n_plus1"
      },
      {
        "from": "c1",
        "to": "n_plus1"
      },
      {
        "from": "vn",
        "to": "rhs_log"
      },
      {
        "from": "rhs_arg",
        "to": "rhs_log"
      },
      {
        "from": "twox_plus_k",
        "to": "rhs_arg"
      },
      {
        "from": "n_plus1",
        "to": "rhs_arg"
      },
      {
        "from": "twox",
        "to": "twox_plus_k"
      },
      {
        "from": "vk",
        "to": "twox_plus_k"
      },
      {
        "from": "c2_const",
        "to": "twox"
      },
      {
        "from": "vx",
        "to": "twox"
      },
      {
        "from": "root_cnt3",
        "to": "top"
      },
      {
        "from": "eq_main",
        "to": "root_cnt3"
      },
      {
        "from": "c3_cnt",
        "to": "root_cnt3"
      },
      {
        "from": "all_n_vals",
        "to": "top"
      },
      {
        "from": "vn1",
        "to": "all_n_vals"
      },
      {
        "from": "vn2",
        "to": "all_n_vals"
      },
      {
        "from": "root_cnt3",
        "to": "all_n_vals"
      }
    ],
    "created_at": "2026-03-23T12:41:01.095Z"
  }
]